[{"id":"427a962b-a896-4330-b4f5-9759fcd267a7","projectId":"70e932c0-cb50-40f9-aba0-ced935f2d5de","name":"g0v hackath66n | 台灣零時政府第陸拾陸次臺南黑客松","type":"實體活動","description":"Welcome to the 66th Hackathon of the g0v community on March 29, 2025！歡迎參加 g0v 黑客松活動！","startDate":"2025-03-29T02:00:00.000Z","endDate":"2025-03-29T09:00:00.000Z","annouceToContributors":false,"location":{"name":"友愛市場二樓 - 好想工作室","address":"台南市中西區友愛街117號2樓"},"link":"https://g0v-jothon.kktix.cc/events/g0v-hackath66n"},{"id":"3dd846f2-b509-4e23-8b4b-d43390f8433a","projectId":"70e932c0-cb50-40f9-aba0-ced935f2d5de","name":"g0v hackath65n | 台灣零時政府第陸拾伍次平凡而自由的黑客松 Ordinary Life with Freedom Hackathon","type":"實體活動","description":"Welcome to the 65th Hackathon of the g0v community on February 22, 2025！歡迎參加 平凡而自由的 g0v 黑客松活動！","startDate":"2025-02-22T01:30:00.000Z","endDate":"2025-02-22T09:30:00.000Z","annouceToContributors":false,"location":{"name":"National Taiwan University Innovation Hall (SPACE M) (國立臺灣大學 學新館 SPACE M)","address":"2F, No. 1, Section 4, Roosevelt Rd, Da’an District, Taipei City (台北市大安區舟山路10巷1弄4號)"},"link":"https://g0v-jothon.kktix.cc/events/g0v-hackath65n"},{"id":"a2f69fb3-a48a-4418-b2a7-b93b074faf3a","projectId":"70e932c0-cb50-40f9-aba0-ced935f2d5de","name":"戶政資料外洩 法庭觀察松","type":"實體活動","description":"2022 年 10 月，有駭客在暗網上以 5000USD 的加密貨幣販售台灣 2300 萬人的戶政資料，至今已過了超過 2 年，但是內政部仍未對此案件做出公開說明，持續不承認戶政外洩發生。","startDate":"2025-02-18T06:30:00.000Z","endDate":"2025-02-18T07:30:00.000Z","annouceToContributors":false,"location":{"name":"台北高等行政法院","address":"台北高等行政法院 111台北市士林區福國路101號"},"link":"https://g0v-jothon.kktix.cc/events/20250218"},{"id":"e377bb9e-38bf-45b0-8b77-c319aa07d0f1","projectId":"70e932c0-cb50-40f9-aba0-ced935f2d5de","name":"20250104 第0次網路黑魔法防禦松","type":"實體活動","description":"網路充滿各種邪惡的黑魔法，兒少色情私密照片買賣、股市詐騙愛情詐騙。許多人深受這些黑魔法的傷害，想邀請有興趣的朋友一起動手協作，共享知識，希望能將 Miffy 的精神傳承下去，保護更多人免於在網路上受害","startDate":"2025-01-04T05:00:00.000Z","endDate":"2025-01-04T09:00:00.000Z","annouceToContributors":false,"location":{"name":"台北 NPO 聚落","address":"台北市中正區重慶南路三段2號"},"link":"https://g0v-jothon.kktix.cc/events/dadath0n"},{"id":"72b279a1-5fbc-4952-b9e7-fffacf46c477","projectId":"70e932c0-cb50-40f9-aba0-ced935f2d5de","name":"g0v hackath64n | 台灣零時政府第陸拾肆次黃金比例黑客松","type":"實體活動","description":"g0v 第陸拾肆次大黑客松將在 2024.11.23（六）於中研院資訊所舉辦，歡迎公民、鄉民、憤青等諸眾，帶著熱血來盡一己之力，開源協作參與社會。","startDate":"2024-11-23T01:30:00.000Z","endDate":"2024-11-23T09:20:00.000Z","annouceToContributors":false,"location":{"name":"中央研究院資訊科學所","address":"台北市南港區研究院路二段128號"},"link":"https://g0v-jothon.kktix.cc/events/g0v-hackath64n"},{"id":"82ab3ef1-3684-43c1-8fb7-9e4d014b102d","projectId":"70e932c0-cb50-40f9-aba0-ced935f2d5de","name":"[取消] g0v 第貳拾陸次基礎建設松","type":"實體活動","description":"g0v 第貳拾陸次基礎建設松將於 11/17（日）14:00 舉行，我們預計進行「g0v 官網更新進度分享與討論」，歡迎一起交流！","startDate":"2024-11-17T06:00:00.000Z","endDate":"2024-11-17T09:00:00.000Z","annouceToContributors":false,"location":{"name":"台北 NPO 聚落 論壇空間","address":"台北市中正區重慶南路三段2號2樓"},"link":"https://g0v-jothon.kktix.cc/events/infrath26n"},{"id":"fc5b9d2c-11f5-4bc2-a3c2-7dfdbd1e45a1","projectId":"70e932c0-cb50-40f9-aba0-ced935f2d5de","name":"g0v 第貳拾伍次基礎建設松","type":"實體活動","description":"g0v 第貳拾伍次基礎建設松將於 10/06（日）14:00 舉行，我們預計討論「g0v 官網視覺化與心得上傳」，歡迎一起交流！","startDate":"2024-10-06T08:00:00.000Z","endDate":"2024-10-06T11:00:00.000Z","annouceToContributors":false,"location":{"name":"台北 NPO 聚落 論壇空間","address":"台北市中正區重慶南路三段2號2樓"},"link":"https://g0v-jothon.kktix.cc/events/infrath25n"},{"id":"01068a46-c3c2-483f-a4c3-11d2c572a426","projectId":"70e932c0-cb50-40f9-aba0-ced935f2d5de","name":"g0v hackath62n | 台灣零時政府第陸拾貳次帶我去月球黑客松","type":"實體活動","description":"g0v 第陸拾貳次大黑客松將在 2024.07.20（六）於中研院資訊所舉辦，歡迎公民、鄉民、憤青等諸眾，帶著熱血來盡一己之力，開源協作參與社會。","startDate":"2024-07-20T01:00:00.000Z","endDate":"2024-07-20T10:00:00.000Z","annouceToContributors":false,"location":{"name":"中央研究院資訊科學所","address":"台北市南港區研究院路二段128號"},"link":"https://g0v-jothon.kktix.cc/events/g0v-hackath62n"},{"id":"19248da0-25f6-4fcf-bbb5-1431f7a7a073","projectId":"70e932c0-cb50-40f9-aba0-ced935f2d5de","name":"零時小學校 2024 夏日線上源力增能營 Sch001 for Source Raising","type":"線上活動","description":"本次「g0v 零時小學校 2024 夏日源力增能營」將一步步帶您認識 g0v 社群，分享這群公民黑客們，是如何用開源精神與行動力，一起用科技解決社會問題！","startDate":"2024-07-06T02:00:00.000Z","endDate":"2024-08-24T09:00:00.000Z","annouceToContributors":false,"location":{"name":"Online Event","address":""},"link":"https://g0v-jothon.kktix.cc/events/sch001ssr2024"},{"id":"10e0ce1b-c9ab-4ee3-b5e8-160387b6ca0e","projectId":"70e932c0-cb50-40f9-aba0-ced935f2d5de","name":"g0v 第貳拾肆次基礎建設松","type":"實體活動","description":"g0v 第貳拾肆次基礎建設松將於 4/20（六）12:00 舉行，我們預計討論「g0v 基礎建設更新機制」，歡迎一起交流！","startDate":"2024-04-20T04:00:00.000Z","endDate":"2024-04-20T07:00:00.000Z","annouceToContributors":false,"location":{"name":"台北 NPO 聚落 社群廚房","address":"台北市中正區重慶南路三段2號4樓"},"link":"https://g0v-jothon.kktix.cc/events/infrath24n"},{"id":"c5f03273-4a29-45dd-8533-a0a907fe6ecb","projectId":"70e932c0-cb50-40f9-aba0-ced935f2d5de","name":"g0v hackath61n | 台灣零時政府第陸拾壹次龍來 Open Data Day 黑客松暨零時小學校 4th 專案孵化競賽決選日","type":"實體活動","description":"g0v 第陸拾壹次大黑客松將在 2024.3.2（六）於臺大學新館二樓 SPACE M 空間舉辦，歡迎公民、鄉民、憤青等諸眾，帶著熱血來盡一己之力，開源協作參與社會。","startDate":"2024-03-02T01:30:00.000Z","endDate":"2024-03-02T10:00:00.000Z","annouceToContributors":false,"location":{"name":"國立臺灣大學學新館二樓 SPACE M 空間","address":"台北市大安區舟山路 10 巷 1 弄 4 號 2 樓"},"link":"https://g0v-jothon.kktix.cc/events/g0v-hackath61n"},{"id":"7f85db8b-e98e-45c0-8cd7-751565b40ff4","projectId":"70e932c0-cb50-40f9-aba0-ced935f2d5de","name":"g0v hackath60n | 台灣零時政府第陸拾次記得投票黑客松","type":"實體活動","description":"g0v 第陸拾次大黑客松將在 2024.01.06（六）於中研院資訊所舉辦，歡迎公民、鄉民、憤青等諸眾，帶著熱血來盡一己之力，開源協作參與社會。","startDate":"2024-01-06T01:30:00.000Z","endDate":"2024-01-06T09:00:00.000Z","annouceToContributors":false,"location":{"name":"中央研究院資訊科學所","address":"台北市南港區研究院路二段128號"},"link":"https://g0v-jothon.kktix.cc/events/g0v-hackath60n"},{"id":"3990f61a-9070-4a84-831e-80eaf34abb26","projectId":"70e932c0-cb50-40f9-aba0-ced935f2d5de","name":"g0v hackath59n | 台灣零時政府第伍拾玖次輪班寫 code 救台灣黑客松","type":"實體活動","description":"g0v 第伍拾玖次大黑客松將在 2023.12.9（六）於新竹縣「竹北市中興里集會所」舉辦，歡迎公民、鄉民、憤青等諸眾，帶著熱血來盡一己之力，開源協作參與社會。","startDate":"2023-12-09T02:00:00.000Z","endDate":"2023-12-09T09:30:00.000Z","annouceToContributors":false,"location":{"name":"竹北市中興里集會所","address":"新竹縣竹北市嘉豐南路一段 11 號"},"link":"https://g0v-jothon.kktix.cc/events/g0v-hackath59n"},{"id":"5b09a537-7cf0-4b05-b0fc-c155b3e392fd","projectId":"70e932c0-cb50-40f9-aba0-ced935f2d5de","name":"g0v hackath58n | 台灣零時政府第伍拾捌次 11 歲生日快樂黑客松","type":"實體活動","description":"g0v 第伍拾捌次大黑客松將在 2023.10.15（六）於中研院資訊所舉辦，歡迎公民、鄉民、憤青等諸眾，帶著熱血來盡一己之力，開源協作參與社會。","startDate":"2023-10-15T01:30:00.000Z","endDate":"2023-10-15T09:00:00.000Z","annouceToContributors":false,"location":{"name":"中央研究院資訊科學所","address":"台北市南港區研究院路二段128號"},"link":"https://g0v-jothon.kktix.cc/events/g0v-hackath58n"},{"id":"088a23b6-52c7-4aac-b867-682e73ce459c","projectId":"70e932c0-cb50-40f9-aba0-ced935f2d5de","name":"g0v hackath57n | 台灣零時政府第伍拾柒次開源普渡黑客松","type":"實體活動","description":"g0v 第伍拾柒次開源普渡黑客松將在 2023.08.26（六）於中研院資訊所舉辦，歡迎公民、鄉民、憤青等諸眾，帶著熱血來盡一己之力，開源協作參與社會。","startDate":"2023-08-26T01:30:00.000Z","endDate":"2023-08-26T09:00:00.000Z","annouceToContributors":false,"location":{"name":"中央研究院資訊科學所","address":"台北市南港區研究院路二段128號"},"link":"https://g0v-jothon.kktix.cc/events/g0v-hackath57n"},{"id":"7afda698-d3a3-46fd-a01e-5cb02793f7b7","projectId":"70e932c0-cb50-40f9-aba0-ced935f2d5de","name":"2023 零時小學校ＸSITCON - 專案實作工作坊","type":"實體活動","description":"零時小學校與 SITCON 學生計算機年會將於 8/12 合辦一日實體「專案實作工作坊」，活動由零時小學校將引導學員從問題思辨與定義、解方發想，到團隊溝通與協作，過程也將安排一組一位隊輔協助專案進行。","startDate":"2023-08-12T02:00:00.000Z","endDate":"2023-08-12T10:00:00.000Z","annouceToContributors":false,"location":{"name":"NPO HUB TAIPEI","address":"台北市中正區重慶南路三段2號"},"link":"https://g0v-jothon.kktix.cc/events/sch001ssr2023-workshop"},{"id":"1039d078-6131-4490-bb41-478be36de4ea","projectId":"70e932c0-cb50-40f9-aba0-ced935f2d5de","name":"零時小學校 2023 夏日線上源力增能營 Sch001 for Source Raising","type":"線上活動","description":"「AI 工具推成出新，我會被取代嗎？教育現場怎麼教？」、「Web3 去中心化時代來臨，會帶來混亂還是希望？」，究竟「如何與科技和平共處？」一起參加零時小學校 2023 夏日線上源力增能營找出生存之道！","startDate":"2023-07-22T02:00:00.000Z","endDate":"2023-08-26T02:00:00.000Z","annouceToContributors":false,"location":{"name":"Online Event","address":""},"link":"https://g0v-jothon.kktix.cc/events/sch001ssr2023"},{"id":"5a3f664b-78ec-49cf-9a44-04327430e3a8","projectId":"70e932c0-cb50-40f9-aba0-ced935f2d5de","name":"g0v 揪松團 | 防衛松前講座 #2 - 躺著也中槍！資訊砲彈下老百姓的生存之道","type":"實體活動","description":"g0v 揪松團將在 7/16（日）舉辦松前講座，我們邀請到了陳廷豪及游知澔分享馬祖斷網及資訊戰經驗，並由《真相製造》作者劉致昕擔任主持人，一起探討資訊砲彈下老百姓的生存之道！","startDate":"2023-07-16T06:00:00.000Z","endDate":"2023-07-16T08:00:00.000Z","annouceToContributors":false,"location":{"name":"青平台「下一步」空間","address":"台北市中正區武昌街一段18號5樓"},"link":"https://g0v-jothon.kktix.cc/events/defense-2"},{"id":"ef8eb21e-83e8-48cf-9a83-75594e3f34a4","projectId":"70e932c0-cb50-40f9-aba0-ced935f2d5de","name":"g0v 揪松團 | 防衛松前講座 #1 - 日常生活轉為戰時避難生活的生存之道","type":"實體活動","description":"防衛黑客松系列活動來啦～g0v 揪松團 將在 7/8（六）舉辦松前講座，我們邀請到了蘇紫雲老師及沈伯洋老師，他們將與您分享「日常生活轉為戰時避難生活的生存之道」！","startDate":"2023-07-08T02:00:00.000Z","endDate":"2023-07-08T04:00:00.000Z","annouceToContributors":false,"location":{"name":"台北 NPO 聚落 社群廚房","address":"台北市中正區重慶南路三段2號4樓"},"link":"https://g0v-jothon.kktix.cc/events/defense-1"},{"id":"48e2586c-7aff-420b-a9ff-1e610729d598","projectId":"70e932c0-cb50-40f9-aba0-ced935f2d5de","name":"g0v hackath56n | 台灣零時政府第伍拾陸次真的假的黑客松 x 水保局","type":"實體活動","description":"g0v 第伍拾陸次真的假的黑客松 x 水保局 將在 2023.07.01（六）於「集思台中新烏日會議中心」舉辦，歡迎公民、鄉民、憤青等諸眾，帶著熱血來盡一己之力，開源協作參與社會。","startDate":"2023-07-01T01:30:00.000Z","endDate":"2023-07-01T09:00:00.000Z","annouceToContributors":false,"location":{"name":"集思台中新烏日會議中心","address":"台中市烏日區高鐵東一路26號4樓"},"link":"https://g0v-jothon.kktix.cc/events/g0v-hackath56n"},{"id":"42d45d21-8a43-4408-9b00-148cf5dbbc02","projectId":"70e932c0-cb50-40f9-aba0-ced935f2d5de","name":"g0v 第貳拾參次基礎建設松","type":"線上活動","description":"g0v 第貳拾參次基礎建設松將於 5/9（二）19:00 舉行，歡迎一起交流、開幹！","startDate":"2023-05-09T11:00:00.000Z","endDate":"2023-05-09T13:30:00.000Z","annouceToContributors":false,"location":{"name":"Online Event","address":""},"link":"https://g0v-jothon.kktix.cc/events/infrath23n"},{"id":"7db3d393-11ae-4f00-bfc3-e984b0525f16","projectId":"70e932c0-cb50-40f9-aba0-ced935f2d5de","name":"g0v 南庄桐花松 2023","type":"實體活動","description":"g0v 南庄桐花松 2023 揪松團想和大家一起出去玩！ 自 2020 年起，#揪松團 和 #數位農民組合 每年共同舉辦「南庄桐花松」，與當地農民進行一場公民科技協作交流。 今年「g0v 南庄桐花松 ","startDate":"2023-04-29T03:00:00.000Z","endDate":"2023-04-30T10:00:00.000Z","annouceToContributors":false,"location":{"name":"數位農民組合大南埔共學空間","address":"苗栗縣南庄鄉南富村大南埔133-1號"},"link":"https://g0v-jothon.kktix.cc/events/tungflowerthon2023"},{"id":"c3905671-8cdc-4421-ad34-857934cd11c4","projectId":"70e932c0-cb50-40f9-aba0-ced935f2d5de","name":"g0v hackath55n | 台灣零時政府第伍拾伍次 AI 也想參加黑客松","type":"實體活動","description":"g0v 第伍拾伍次大黑客松將在 2023.04.08（六）於中研院資訊所舉辦，歡迎公民、鄉民、憤青等諸眾，帶著熱血來盡一己之力，開源協作參與社會。","startDate":"2023-04-08T01:30:00.000Z","endDate":"2023-04-08T09:00:00.000Z","annouceToContributors":false,"location":{"name":"中央研究院資訊科學所","address":"台北市南港區研究院路二段128號"},"link":"https://g0v-jothon.kktix.cc/events/g0v-hackath55n"},{"id":"349b33d7-98db-461c-83e9-3f2b136998e9","projectId":"70e932c0-cb50-40f9-aba0-ced935f2d5de","name":"g0v 第貳拾貳次基礎建設松","type":"實體活動","description":"g0v 第貳拾貳次基礎建設松將於 3/4（六）13:30 舉行，歡迎自由登記提案，一起交流、開幹！","startDate":"2023-03-04T05:30:00.000Z","endDate":"2023-03-04T09:00:00.000Z","annouceToContributors":false,"location":{"name":"NPO HUB 2 樓影響力工場","address":"台北市中正區重慶南路三段2號"},"link":"https://g0v-jothon.kktix.cc/events/infrath22n"},{"id":"47b6b56a-3211-48b8-a04b-590fcadc3401","projectId":"70e932c0-cb50-40f9-aba0-ced935f2d5de","name":"g0v hackath54n | 台灣零時政府第伍拾肆次兔兔黑客松暨零時小學校專案孵化競賽決選日","type":"實體活動","description":"g0v 第伍拾肆次大黑客松將在 2023.02.11（六）於國教院臺北院區舉辦，歡迎公民、鄉民、憤青等諸眾，帶著熱血來盡一己之力，開源協作參與社會。","startDate":"2023-02-11T01:30:00.000Z","endDate":"2023-02-11T09:00:00.000Z","annouceToContributors":false,"location":{"name":"國家教育研究院 臺北院區","address":"台北市大安區和平東路一段179號"},"link":"https://g0v-jothon.kktix.cc/events/g0v-hackath54n"},{"id":"d41ff1d1-bf65-4540-a11c-e35b72e92a9a","projectId":"70e932c0-cb50-40f9-aba0-ced935f2d5de","name":"g0v hackath53n | 台灣零時政府第伍拾參次 18 歲公民權黑客松","type":"實體活動","description":"g0v 第伍拾參次黑客松將在 2022.12.17（六）於中研院資訊所舉辦，歡迎公民、鄉民、憤青等諸眾，帶著熱血來盡一己之力，開源協作參與社會。","startDate":"2022-12-17T01:30:00.000Z","endDate":"2022-12-17T09:00:00.000Z","annouceToContributors":false,"location":{"name":"中央研究院資訊科學所","address":"台北市南港區研究院路二段128號"},"link":"https://g0v-jothon.kktix.cc/events/g0v-hackath53n"},{"id":"13787ad6-6fe4-46e0-a6b8-9bf0a459b13a","projectId":"70e932c0-cb50-40f9-aba0-ced935f2d5de","name":"［零時小學校新竹源力增能工作坊］公民科技探究與實作課程設計","type":"實體活動","description":"探究與實作課程如何更跨領域並與真實社會連結？活動邀請 LASS 創辦人哈爸與善於跨領域教學的竹東高中韓中梅老師引導大家，一同嘗試把公民科技專案融入探究與實作課程！","startDate":"2022-11-27T02:00:00.000Z","endDate":"2022-11-27T07:00:00.000Z","annouceToContributors":false,"location":{"name":"國立竹東高中","address":"新竹縣竹東鎮大林路2號"},"link":"https://g0v-jothon.kktix.cc/events/ssr2022hsinchu"},{"id":"652cdb3d-f3b6-49a3-acd6-8ae10d1d387f","projectId":"70e932c0-cb50-40f9-aba0-ced935f2d5de","name":"g0v hackath52n | 台灣零時政府第伍拾貳次十週年黑客松＆論壇＆生日趴","type":"實體活動","description":"g0v 第伍拾貳次十週年黑客松 將在 2022.10.22（六）於「中央研究院 人文館 第一、二會議室」舉辦，歡迎公民、鄉民、憤青等諸眾，帶著熱血來盡一己之力，開源協作參與社會。","startDate":"2022-10-21T10:30:00.000Z","endDate":"2022-10-23T09:00:00.000Z","annouceToContributors":false,"location":{"name":"","address":""},"link":"https://g0v-jothon.kktix.cc/events/g0v-hackath52n"},{"id":"0e0786c9-d304-4f58-879d-548cc054c6d2","projectId":"70e932c0-cb50-40f9-aba0-ced935f2d5de","name":"數位洄瀾黑客松","type":"實體活動","description":"數位洄瀾黑客松 將在 2022.09.24（六）於「花蓮縣政府 1 樓大禮堂」舉辦，歡迎公民、鄉民、憤青等諸眾，帶著熱血來盡一己之力，開源協作參與社會。","startDate":"2022-09-24T02:00:00.000Z","endDate":"2022-09-24T09:00:00.000Z","annouceToContributors":false,"location":{"name":"花蓮縣政府一樓大禮堂","address":"花蓮市府前路 17 號"},"link":"https://g0v-jothon.kktix.cc/events/g0v-hualienthon2022"},{"id":"f8ad1792-4630-4b34-84c3-d82a5768b0dd","projectId":"70e932c0-cb50-40f9-aba0-ced935f2d5de","name":"g0v 第貳拾壹次基礎建設松","type":"線上活動","description":"g0v 第貳拾壹次基礎建設松將於 9/3（六）13:30 舉行，歡迎自由登記提案，一起交流、開幹！","startDate":"2022-09-03T05:30:00.000Z","endDate":"2022-09-03T09:30:00.000Z","annouceToContributors":false,"location":{"name":"Online Event","address":""},"link":"https://g0v-jothon.kktix.cc/events/infrath21n"},{"id":"0746d735-3afe-487f-aeb8-bb0ce53181b0","projectId":"70e932c0-cb50-40f9-aba0-ced935f2d5de","name":"g0v hackath51n | 台灣零時政府第伍拾壹次大肚山海豚黑客松 x 水保局","type":"實體活動","description":"g0v 第伍拾壹次大肚山海豚黑客松 x 水保局 將在 2022.08.20（六）於「集思台中新烏日會議中心」舉辦，歡迎公民、鄉民、憤青等諸眾，帶著熱血來盡一己之力，開源協作參與社會。","startDate":"2022-08-20T01:30:00.000Z","endDate":"2022-08-20T09:00:00.000Z","annouceToContributors":false,"location":{"name":"集思台中新烏日會議中心","address":"台中市烏日區高鐵東一路26號4樓"},"link":"https://g0v-jothon.kktix.cc/events/g0v-hackath51n"},{"id":"c416f34c-8ddc-44d5-ac63-01364ab97744","projectId":"70e932c0-cb50-40f9-aba0-ced935f2d5de","name":"零時小學校 2022 夏日線上源力增能營 Sch001 for Source Raising","type":"實體活動","description":"g0v 如何協作出 818+ 件各領域的專案？來零時小學校 2022 夏日源力增能營找答案吧！ 7/24-8/27 你將經歷 22 堂數位公民課程、專題實作，培養數位公民力、共好行動力、跨界自學力！","startDate":"2022-07-24T01:00:00.000Z","endDate":"2022-08-27T10:00:00.000Z","annouceToContributors":false,"location":{"name":"","address":""},"link":"https://g0v-jothon.kktix.cc/events/sch001ssr2022"},{"id":"0b6698bb-60e5-4f4a-b47a-c47e2e18143a","projectId":"70e932c0-cb50-40f9-aba0-ced935f2d5de","name":"g0v 第貳拾次基礎建設松","type":"實體活動","description":"g0v 第貳拾次基礎建設松將於 7/9（六）10:00 舉行，歡迎自由登記提案，一起交流、開幹！","startDate":"2022-07-09T02:00:00.000Z","endDate":"2022-07-09T07:00:00.000Z","annouceToContributors":false,"location":{"name":"NPO HUB 2 樓影響力論壇","address":"台北市中正區重慶南路三段2號"},"link":"https://g0v-jothon.kktix.cc/events/infrath20n"},{"id":"dd48a0b6-9223-49c9-9c7c-5cfde0ea8990","projectId":"70e932c0-cb50-40f9-aba0-ced935f2d5de","name":"g0v hackath50n | 台灣零時政府第伍拾次來電五十黑客松 x COSCUP Open Source Contributor Workshop","type":"實體活動","description":"g0v 第伍拾次來電五十黑客松 x COSCUP 將在 2022.06.18（六）於升級會議中心-松江 101 館舉辦，歡迎公民、鄉民、憤青等諸眾，帶著熱血來盡一己之力，開源協作參與社會。","startDate":"2022-06-18T01:30:00.000Z","endDate":"2022-06-18T09:00:00.000Z","annouceToContributors":false,"location":{"name":"升級會議中心-松江101館","address":"台北市中山區松江路101號4樓"},"link":"https://g0v-jothon.kktix.cc/events/g0v-hackath50n"},{"id":"89f3c8d5-a3f8-464e-9fc5-f2bba3f742f0","projectId":"70e932c0-cb50-40f9-aba0-ced935f2d5de","name":"g0v 南庄桐花松 2022","type":"實體活動","description":"g0v 南庄桐花松 2022   2020 年，#揪松團 與 #數位農民組合 合辦了「南庄桐花松」，在「大南埔共學空間」開啟與「真 ● 農民」的公民科技協作交流，探討因時 / 因地制宜的台灣版農夫種植","startDate":"2022-05-01T02:00:00.000Z","endDate":"2022-05-01T10:00:00.000Z","annouceToContributors":false,"location":{"name":"數位農民組合大南埔共學空間","address":"苗栗縣南庄鄉南富村大南埔133-1號"},"link":"https://g0v-jothon.kktix.cc/events/tungflowerthon2022"},{"id":"bf78445f-392b-4044-9ecb-0a313477ea63","projectId":"70e932c0-cb50-40f9-aba0-ced935f2d5de","name":"g0v hackath49n | 台灣零時政府第肆拾玖次全糖去冰黑客松 x 2022 亞太社會創新高峰會","type":"實體活動","description":"g0v 第肆拾貳次大黑客松將在 2022.04.09（六）於台南 C-Hub 成大創意中心舉辦，歡迎公民、鄉民、憤青等諸眾，帶著熱血來盡一己之力，開源協作參與社會。","startDate":"2022-04-09T02:00:00.000Z","endDate":"2022-04-09T10:00:00.000Z","annouceToContributors":false,"location":{"name":"C-Hub 成大創新中心","address":"C-Hub 成大創新中心"},"link":"https://g0v-jothon.kktix.cc/events/g0v-hackath49n"},{"id":"f9c11488-0a29-4a7c-88ac-171151fc4811","projectId":"70e932c0-cb50-40f9-aba0-ced935f2d5de","name":"g0v 第拾玖次基礎建設松","type":"實體活動","description":"g0v 第拾柒次基礎建設松將於 03/12（六）13:30 舉行，歡迎自由登記提案，一起交流、開幹！","startDate":"2022-03-12T05:30:00.000Z","endDate":"2022-03-12T09:30:00.000Z","annouceToContributors":false,"location":{"name":"NPO HUB 2 樓影響力論壇","address":"台北市中正區重慶南路三段2號"},"link":"https://g0v-jothon.kktix.cc/events/infrath19n"},{"id":"b33463a9-c666-4226-b3d5-b62f8d761133","projectId":"70e932c0-cb50-40f9-aba0-ced935f2d5de","name":"g0v hackath48n | 台灣零時政府第肆拾捌次虎來俱進黑客松","type":"實體活動","description":"g0v 第肆拾捌次大黑客松將在 2022.2.19（六）於 Gather Town 線上會議室舉辦，歡迎公民、鄉民、憤青等諸眾，帶著熱血運用一己之力，開源協作參與社會。","startDate":"2022-02-19T02:00:00.000Z","endDate":"2022-02-19T09:00:00.000Z","annouceToContributors":false,"location":{"name":"","address":""},"link":"https://g0v-jothon.kktix.cc/events/g0v-hackath48n"},{"id":"6aaccfc6-4e7b-4ec7-8633-860f1382c1ce","projectId":"70e932c0-cb50-40f9-aba0-ced935f2d5de","name":"g0v hackath47n | 台灣零時政府第肆拾柒次板橋油庫口黑客松","type":"實體活動","description":"g0v 第肆拾柒次大黑客松將在 2021.12.11（六）於線上舉辦，歡迎公民、鄉民、憤青等諸眾，帶著熱血來盡一己之力，開源協作參與社會。","startDate":"2021-12-11T01:00:00.000Z","endDate":"2021-12-11T10:00:00.000Z","annouceToContributors":false,"location":{"name":"新板傑仕堡A棟2樓（新北板橋中山國中大門對面）","address":"新北市板橋區文化路一段188巷57號"},"link":"https://g0v-jothon.kktix.cc/events/g0v-hackath47n"},{"id":"17ddc4de-78d8-4701-8bed-3517b2a79858","projectId":"70e932c0-cb50-40f9-aba0-ced935f2d5de","name":"［零時小學校 × LASS］新竹小松","type":"實體活動","description":"緣起 零時小學校的實體活動回來了！這次我們要到新竹，試著將土地、河流與流域轉化為地理資料，用地理資訊系統說一個新竹的流域故事⋯⋯ 本次零時小學校的「新竹小松」將與 LASS 開源公益環境感測網路合作，","startDate":"2021-11-20T05:30:00.000Z","endDate":"2021-11-20T10:00:00.000Z","annouceToContributors":false,"location":{"name":"慕溪園","address":"新竹縣竹北市復興三路二段 82 號"},"link":"https://g0v-jothon.kktix.cc/events/sch001-hc211120"},{"id":"4e25f529-260b-4ce4-9ce4-0c0470169512","projectId":"70e932c0-cb50-40f9-aba0-ced935f2d5de","name":"g0v hackath46n | 台灣零時政府第肆拾陸次九週年黑客松","type":"實體活動","description":"g0v 第肆拾陸次大黑客松將在 2021.10.23（六）於線上舉辦，歡迎公民、鄉民、憤青等諸眾，帶著熱血來盡一己之力，開源協作參與社會。","startDate":"2021-10-23T01:00:00.000Z","endDate":"2021-10-23T09:00:00.000Z","annouceToContributors":false,"location":{"name":"集思交通部國際會議中心 3F 國際會議廳／GIS MOTC 3F Plenary Hall","address":"台北市杭州南路一段24號"},"link":"https://g0v-jothon.kktix.cc/events/g0v-hackath46n"},{"id":"fa566ce9-7990-4cc7-96de-e67cb88519bb","projectId":"70e932c0-cb50-40f9-aba0-ced935f2d5de","name":"g0v hackath45n | 台灣零時政府第肆拾伍次原本在台中黑客松","type":"實體活動","description":"g0v 第肆拾伍次大黑客松將在 2021.08.21（六）於線上舉辦，歡迎公民、鄉民、憤青等諸眾，帶著熱血來盡一己之力，開源協作參與社會。","startDate":"2021-08-21T02:00:00.000Z","endDate":"2021-08-21T09:00:00.000Z","annouceToContributors":false,"location":{"name":"","address":""},"link":"https://g0v-jothon.kktix.cc/events/g0v-hackath45n"},{"id":"4bc71a4c-8ec3-4407-b2a2-b0fd77a9880a","projectId":"70e932c0-cb50-40f9-aba0-ced935f2d5de","name":"【選修課】零時小學校「夏日源理」2021 線上源力增能營 Sch001 for Source Raising","type":"實體活動","description":"零時小學校「夏日源理」2021 線上源力增能營是 g0v 貢獻者與 g0v 揪松團協作推出的線上課程計畫，以「開源、協作、開放學習」為主軸，期盼以開放的方式，在線上陪伴所有學習者。","startDate":"2021-07-17T01:00:00.000Z","endDate":"2021-08-14T10:00:00.000Z","annouceToContributors":false,"location":{"name":"","address":""},"link":"https://g0v-jothon.kktix.cc/events/codeforssrelective"},{"id":"c4113b0c-8b4c-4c50-ab10-337f04b6398d","projectId":"70e932c0-cb50-40f9-aba0-ced935f2d5de","name":"零時小學校「夏日源理」2021 線上源力增能營 Sch001 for Source Raising","type":"實體活動","description":"零時小學校「夏日源理」2021 線上源力增能營是 g0v 貢獻者與 g0v 揪松團協作推出的線上課程計畫，以「開源、協作、開放學習」為主軸，期盼以開放的方式，在線上陪伴所有學習者。","startDate":"2021-07-17T01:00:00.000Z","endDate":"2021-08-14T10:00:00.000Z","annouceToContributors":false,"location":{"name":"","address":""},"link":"https://g0v-jothon.kktix.cc/events/sch001ssr2021"},{"id":"7eab5ff9-f39e-453b-b3d2-0a934f3492f4","projectId":"70e932c0-cb50-40f9-aba0-ced935f2d5de","name":"g0v hackath44n | 台灣零時政府第肆拾肆次世界最危險黑客松","type":"實體活動","description":"g0v 第肆拾肆次大黑客松將在 2021.06.26（六）於線上舉辦，歡迎公民、鄉民、憤青等諸眾，帶著熱血來盡一己之力，開源協作參與社會。","startDate":"2021-06-26T01:00:00.000Z","endDate":"2021-06-26T09:00:00.000Z","annouceToContributors":false,"location":{"name":"","address":""},"link":"https://g0v-jothon.kktix.cc/events/g0v-hackath44n"},{"id":"fe9119b2-0458-4613-a92f-d16d36fc12c0","projectId":"70e932c0-cb50-40f9-aba0-ced935f2d5de","name":"「線上活動怎麼辦？」線上協作工作坊","type":"實體活動","description":"這是一場，教你怎麼辦線上活動的，線上工作坊。","startDate":"2021-06-19T11:30:00.000Z","endDate":"2021-06-19T13:30:00.000Z","annouceToContributors":false,"location":{"name":"","address":""},"link":"https://g0v-jothon.kktix.cc/events/coworkshop2021"},{"id":"71a6811f-a10c-4318-a278-1a749f29f2d3","projectId":"70e932c0-cb50-40f9-aba0-ced935f2d5de","name":"g0v infrath18n 第拾捌次基礎建設松","type":"實體活動","description":"g0v 第拾捌次基礎建設松將於 05/22（六）14:00 「線上」舉行，歡迎自由登記提案，一起交流、開幹！","startDate":"2021-05-22T06:00:00.000Z","endDate":"2021-05-22T10:00:00.000Z","annouceToContributors":false,"location":{"name":"","address":""},"link":"https://g0v-jothon.kktix.cc/events/infrath18n"},{"id":"63369ffb-c42b-4168-a7cc-7057112e4d84","projectId":"70e932c0-cb50-40f9-aba0-ced935f2d5de","name":"g0v hackath44n | 台灣零時政府第肆拾肆次世界最危險黑客松","type":"實體活動","description":"g0v 第肆拾肆次大黑客松將在 2021.05.22（六）於中研院資訊所舉辦，歡迎公民、鄉民、憤青等諸眾，帶著熱血來盡一己之力，開源協作參與社會。","startDate":"2021-05-22T01:00:00.000Z","endDate":"2021-05-22T10:00:00.000Z","annouceToContributors":false,"location":{"name":"中央研究院資訊科學所","address":"台北市南港區研究院路二段128號"},"link":"https://g0v-jothon.kktix.cc/events/g0v-hackath44narchived"},{"id":"1f07b93d-a223-4dba-9ba2-f6df912cb5ae","projectId":"70e932c0-cb50-40f9-aba0-ced935f2d5de","name":"g0v 南庄桐花松 2021","type":"實體活動","description":"g0v 南庄桐花松 2021，農業、賞花、Hacking！","startDate":"2021-05-01T02:00:00.000Z","endDate":"2021-05-01T10:00:00.000Z","annouceToContributors":false,"location":{"name":"","address":""},"link":"https://g0v-jothon.kktix.cc/events/tungflowerthon2021"},{"id":"01527151-19aa-4c09-b967-776c2ae97758","projectId":"70e932c0-cb50-40f9-aba0-ced935f2d5de","name":"g0v Hackath43n | 台灣零時政府第肆拾參次源力犇騰黑客松","type":"實體活動","description":"g0v 第肆拾參次大黑客松將在 2021.03.20（六）於中研院資訊所舉辦，歡迎公民、鄉民、憤青等諸眾，帶著熱血來盡一己之力，開源協作參與社會。","startDate":"","endDate":"","annouceToContributors":false,"location":{"name":"中央研究院資訊科學所","address":"台北市南港區研究院路二段128號"},"link":"https://g0v-jothon.kktix.cc/events/g0v-hackath43n"},{"id":"a7c74ed2-db69-4b40-89a1-f1d82be5eec1","projectId":"70e932c0-cb50-40f9-aba0-ced935f2d5de","name":"小學校松 Sch001 2021 Workshop I","type":"實體活動","description":"零時小學校的 2021 年第一次「小學校松」將於 02/20（六）14:00 舉行，歡迎一起來交流和協作！","startDate":"2021-02-20T06:00:00.000Z","endDate":"2021-02-20T10:00:00.000Z","annouceToContributors":false,"location":{"name":"NPO HUB Taipei","address":"台北市中正區重慶南路三段2號"},"link":"https://g0v-jothon.kktix.cc/events/sch001-2021-wsi"},{"id":"c7fd44e8-3925-49b4-b520-fa75b4f5f857","projectId":"70e932c0-cb50-40f9-aba0-ced935f2d5de","name":"g0v hackath42n | 台灣零時政府第肆拾貳次生命、宇宙以及萬事萬物的終極答案黑客松","type":"實體活動","description":"g0v 第肆拾貳次大黑客松將在 2021.01.23（六）於中研院資訊所舉辦，歡迎公民、鄉民、憤青等諸眾，帶著熱血來盡一己之力，開源協作參與社會。","startDate":"2021-01-23T01:00:00.000Z","endDate":"2021-01-23T10:00:00.000Z","annouceToContributors":false,"location":{"name":"中央研究院資訊科學所","address":"台北市南港區研究院路二段128號"},"link":"https://g0v-jothon.kktix.cc/events/g0v-hackath42n"},{"id":"2c5b1fc0-4003-4802-aa8e-46e5d5ae3c0a","projectId":"70e932c0-cb50-40f9-aba0-ced935f2d5de","name":"g0v 第拾柒次基礎建設松","type":"實體活動","description":"g0v 第拾柒次基礎建設松將於 01/10（日）14:00 舉行，歡迎自由登記提案，一起交流、開幹！","startDate":"2021-01-10T06:00:00.000Z","endDate":"2021-01-10T10:00:00.000Z","annouceToContributors":false,"location":{"name":"NPO Hub 4F Kitchen","address":"台北市中正區重慶南路三段2號"},"link":"https://g0v-jothon.kktix.cc/events/infrath17n"},{"id":"0d602d01-c30c-40f2-a5f2-818e5ea59e20","projectId":"70e932c0-cb50-40f9-aba0-ced935f2d5de","name":"g0v hackath41n | 台灣零時政府第肆拾壹次八週年黑客松","type":"實體活動","description":"歡迎公民、鄉民、憤青、開發者、設計者、社會運動工作者、公務員、法律專家、文字工作者、插畫家與媒體工作者等諸眾，帶著熱血來盡一己之力，開源協作參與社會。","startDate":"2020-10-24T01:00:00.000Z","endDate":"2020-10-24T10:00:00.000Z","annouceToContributors":false,"location":{"name":"中央研究院資訊科學所","address":"台北市南港區研究院路二段128號"},"link":"https://g0v-jothon.kktix.cc/events/g0v-hackath41n"},{"id":"f8673956-e353-4d64-ae40-fea9c21c7287","projectId":"70e932c0-cb50-40f9-aba0-ced935f2d5de","name":"零時小學校 Demo Day 2020","type":"實體活動","description":"零時小學校（Sch001）是聚焦在教育的 g0v 專案，將代表數位原生世代的 0 與 1 放入代表教育的「學校（School）」，從零重新思考學校的角色，代表教育與數位社群的連結與協作。","startDate":"2020-08-30T05:30:00.000Z","endDate":"2020-08-30T10:00:00.000Z","annouceToContributors":false,"location":{"name":"華山 1914 文化創意產業園區中 3 館 2 樓拱廳","address":"台北市中正區八德路一段1號"},"link":"https://g0v-jothon.kktix.cc/events/sch001-demo-2020"},{"id":"dca03c24-0839-4e64-8f95-fa9b4cacf311","projectId":"70e932c0-cb50-40f9-aba0-ced935f2d5de","name":"g0v hackath40n | 台灣零時政府第肆拾次集合啦！老地方黑客松","type":"實體活動","description":"歡迎公民、鄉民、憤青、開發者、設計者、社會運動工作者、公務員、法律專家、文字工作者、插畫家與媒體工作者等諸眾，帶著熱血來盡一己之力，開源協作參與社會。","startDate":"2020-07-25T01:00:00.000Z","endDate":"2020-07-25T10:00:00.000Z","annouceToContributors":false,"location":{"name":"中研院資訊所","address":"11529台灣台北市南港區研究院路二段128號"},"link":"https://g0v-jothon.kktix.cc/events/g0v-hackath40n"},{"id":"fdbea087-2526-4119-bf6a-1163b89c2775","projectId":"70e932c0-cb50-40f9-aba0-ced935f2d5de","name":"零時小學校：第三次工作坊 Sch001 Workshop III","type":"實體活動","description":"零時小學校（Sch001）是聚焦在教育的 g0v 專案，將代表數位原生世代的 0 與 1 放入代表教育的「學校（School）」，從零重新思考學校的角色，代表教育與數位社群的連結與協作。","startDate":"2020-06-21T06:00:00.000Z","endDate":"2020-06-21T11:00:00.000Z","annouceToContributors":false,"location":{"name":"台北 NPO 聚落","address":"NPO HUB Taipei 4F Kitchen Lab"},"link":"https://g0v-jothon.kktix.cc/events/sch001-wsiii"},{"id":"00d8bd89-b00f-4f13-9326-6313fabf6d68","projectId":"70e932c0-cb50-40f9-aba0-ced935f2d5de","name":"g0v 南庄桐花松","type":"實體活動","description":"g0v 南庄桐花松，邊吃邊聊邊 Hacking！","startDate":"2020-05-16T02:00:00.000Z","endDate":"2020-05-16T10:00:00.000Z","annouceToContributors":false,"location":{"name":"苗栗南庄南埔國小","address":"苗栗縣南庄鄉南富村134號"},"link":"https://g0v-jothon.kktix.cc/events/tungflowerthon"},{"id":"a235760c-ee43-4aa2-89a9-93d429c1298a","projectId":"70e932c0-cb50-40f9-aba0-ced935f2d5de","name":"零時小學校：三月大松日 Sch001 @ g0v Hackath38n","type":"實體活動","description":"零時小學校（Sch001）是聚焦在教育的 g0v 專案，將代表數位原生世代的 0 與 1 放入代表教育的「學校（School）」，從零重新思考學校的角色，代表教育與數位社群的連結與協作。","startDate":"2020-03-14T01:00:00.000Z","endDate":"2020-03-14T10:00:00.000Z","annouceToContributors":false,"location":{"name":"台北 NPO 聚落","address":"NPO HUB Taipei 4F Kitchen"},"link":"https://g0v-jothon.kktix.cc/events/sch001-hackath38n"},{"id":"ee81d92e-4e75-4266-838e-45547d758175","projectId":"70e932c0-cb50-40f9-aba0-ced935f2d5de","name":"2020 g0v 坑抗 Keng of Conf ── 坑主小聚","type":"實體活動","description":"g0v 揪松團想舉辦坑主小聚（a.k.a. g0v Keng of Conf 簡稱「坑抗」），希望可以給不同階段的坑主（初坑、中坑或深坑）一些經驗分享或共同討論解決方式。","startDate":"2020-02-02T06:00:00.000Z","endDate":"2020-02-02T10:00:00.000Z","annouceToContributors":false,"location":{"name":"","address":""},"link":"https://g0v-jothon.kktix.cc/events/kengconf01"},{"id":"018138af-59d3-4cc4-bab6-d8442f709846","projectId":"70e932c0-cb50-40f9-aba0-ced935f2d5de","name":"「US Taiwan Watch：美國國會台灣觀測站」首次台灣分享會","type":"實體活動","description":"「US Taiwan Watch：美國國會台灣觀測站」首次台灣分享會來了！","startDate":"2020-01-18T11:00:00.000Z","endDate":"2020-01-18T13:00:00.000Z","annouceToContributors":false,"location":{"name":"台北NPO聚落","address":"NPO HUB Taipei 4F 大廳"},"link":"https://g0v-jothon.kktix.cc/events/ustwatch2020tp"},{"id":"0b30eac1-7fa7-4598-8f7f-0aa5c52e63a3","projectId":"70e932c0-cb50-40f9-aba0-ced935f2d5de","name":"g0v 第拾伍次基礎建設松","type":"實體活動","description":"g0v 第拾伍次基礎建設松將於 01/18（六）14:00 舉行，歡迎自由登記提案，一起交流、開幹、吃午餐！","startDate":"2020-01-18T06:00:00.000Z","endDate":"2020-01-18T10:00:00.000Z","annouceToContributors":false,"location":{"name":"NPO Hub ","address":"台北市中正區重慶南路三段2號"},"link":"https://g0v-jothon.kktix.cc/events/infrath15n"},{"id":"1cee8712-f8f9-4464-a702-80f70fde8c55","projectId":"70e932c0-cb50-40f9-aba0-ced935f2d5de","name":"g0v hackath37n | 台灣零時政府第參拾柒次全臺首學黑客松","type":"實體活動","description":"歡迎公民、鄉民、憤青、開發者、設計者、社會運動工作者、公務員、法律專家、文字工作者、插畫家與媒體工作者等諸眾，帶著熱血來盡一己之力，開源協作參與社會。","startDate":"2019-12-21T01:00:00.000Z","endDate":"2019-12-21T10:00:00.000Z","annouceToContributors":false,"location":{"name":"吳園藝文中心","address":"台南市中西區民權路二段30號"},"link":"https://g0v-jothon.kktix.cc/events/g0v-hackath37n"},{"id":"5e45b7bc-c2de-4a7b-b602-ac6aaa53eb81","projectId":"70e932c0-cb50-40f9-aba0-ced935f2d5de","name":"g0v 台南新手村：首場台南大松說明會","type":"實體活動","description":"「g0v 是什麼？」如果你對 g0v 黑客松有過上述疑問，g0v 首場台南大松說明會「g0v 台南新手村」就是你可以來參加的活動囉！","startDate":"2019-11-30T06:00:00.000Z","endDate":"2019-11-30T08:00:00.000Z","annouceToContributors":false,"location":{"name":"好想工作室","address":"台南市東區北門路二段16號L2A"},"link":"https://g0v-jothon.kktix.cc/events/g0villagetainan"},{"id":"407189a7-f875-49dc-a321-e7c1e2d301b4","projectId":"70e932c0-cb50-40f9-aba0-ced935f2d5de","name":"g0v Year-End Banquet | g0v 公民科技創新獎助金 2019 成果發表會暨 g0v 社群忘年會","type":"實體活動","description":"g0v 社群首次忘年會！活動包含「g0v 公民科技創新獎助金」今年獲獎團隊的成果發表會、g0v 社群閃電講與義賣競拍，邀請所有熱血公民，與 g0v 社群參與者一同參加這場史無前例的宴會。","startDate":"2019-11-16T06:00:00.000Z","endDate":"2019-11-16T11:00:00.000Z","annouceToContributors":false,"location":{"name":"華山文創園區中 3 館 2 樓拱廳","address":"台北市中正區八德路一段1號"},"link":"https://g0v-jothon.kktix.cc/events/g0v-year-end-banquet-2019"},{"id":"0537f5d8-7ad9-4786-8a5f-868a19e8259f","projectId":"70e932c0-cb50-40f9-aba0-ced935f2d5de","name":"g0v 第拾肆次基礎建設松","type":"實體活動","description":"g0v 第拾肆次基礎建設松將於 10/20（日）10:00 舉行，歡迎自由登記提案，一起交流、開幹、吃午餐！","startDate":"2019-10-20T02:00:00.000Z","endDate":"2019-10-20T10:00:00.000Z","annouceToContributors":false,"location":{"name":"NPO Hub ","address":"台北市中正區重慶南路三段2號"},"link":"https://g0v-jothon.kktix.cc/events/infrath14n"},{"id":"13bc13e8-c2f9-4670-b9f9-1379567b7cda","projectId":"70e932c0-cb50-40f9-aba0-ced935f2d5de","name":"g0v hackath36n | 台灣零時政府第參拾陸次開放台北市議會黑客松","type":"實體活動","description":"歡迎公民、鄉民、憤青、開發者、設計者、社會運動工作者、公務員、法律專家、文字工作者、插畫家與媒體工作者等諸眾，帶著熱血來盡一己之力，開源協作參與社會。","startDate":"2019-09-07T01:00:00.000Z","endDate":"2019-09-07T10:00:00.000Z","annouceToContributors":false,"location":{"name":"台北市議會","address":"台北市信義區仁愛路四段507號"},"link":"https://g0v-jothon.kktix.cc/events/g0v-hackath36n"},{"id":"40b4447c-af25-4a16-ae63-e55bc4f51a6a","projectId":"70e932c0-cb50-40f9-aba0-ced935f2d5de","name":"g0v hackath35n | 台灣零時政府第參拾伍次最旁邊黑客松","type":"實體活動","description":"歡迎公民、鄉民、憤青、開發者、設計者、社會運動工作者、公務員、法律專家、文字工作者、插畫家與媒體工作者等諸眾，帶著熱血來盡一己之力，開源協作參與社會。","startDate":"2019-07-20T01:00:00.000Z","endDate":"2019-07-20T10:00:00.000Z","annouceToContributors":false,"location":{"name":"中央研究院資訊科學所","address":"台北市南港區研究院路二段128號"},"link":"https://g0v-jothon.kktix.cc/events/g0v-hackath35n"},{"id":"18668a64-6918-498c-aeb0-78788eec6278","projectId":"70e932c0-cb50-40f9-aba0-ced935f2d5de","name":"第壹次電視松 × 公視       hackatv1n × PTS","type":"實體活動","description":"繼四月第零次《電視松》，這次第壹次《電視松》與公視合作，對於現在電視新聞環境感到不滿，有想法想要動手做事的，或是沒想法但想幫幫忙的，都歡迎可以來參加！","startDate":"2019-06-22T01:30:00.000Z","endDate":"2019-06-22T09:30:00.000Z","annouceToContributors":false,"location":{"name":"公視 A 棟 2 樓永久會員聯誼室","address":"114台北市內湖區康寧路三段75巷50號"},"link":"https://g0v-jothon.kktix.cc/events/hackatv1n"},{"id":"eb6b7855-54c8-4502-8d84-cfac0d54cb9c","projectId":"70e932c0-cb50-40f9-aba0-ced935f2d5de","name":"g0v hackath34n | 台灣零時政府第參拾肆次再開放空總黑客松","type":"實體活動","description":"歡迎公民、鄉民、憤青、開發者、設計者、社會運動工作者、公務員、法律專家、文字工作者、插畫家與媒體工作者等諸眾，帶著熱血來盡一己之力，開源協作參與社會。","startDate":"2019-05-25T01:00:00.000Z","endDate":"2019-05-25T10:00:00.000Z","annouceToContributors":false,"location":{"name":"空總臺灣當代文化實驗場·聯合餐廳","address":"106台北市大安區建國南路一段177號"},"link":"https://g0v-jothon.kktix.cc/events/g0v-hackath34n"},{"id":"150580d5-8400-41a8-b477-f23252c09b5c","projectId":"70e932c0-cb50-40f9-aba0-ced935f2d5de","name":"第零次電視松","type":"實體活動","description":"電視媒體至今仍有很大的影響力，無論是在小吃店內或是家中客廳。但現在的電視媒體充滿許多亂象。該是由政府來管控，還是要透過市場機制，又或是要推動媒體自律？怎麼做？來電視松討論協作吧～","startDate":"2019-04-28T06:00:00.000Z","endDate":"2019-04-28T10:00:00.000Z","annouceToContributors":false,"location":{"name":"群島 archipiélago","address":"圓山花博爭艷館"},"link":"https://g0v-jothon.kktix.cc/events/hackatv0n"},{"id":"20a6f43a-af4a-4085-95e8-a9e892625843","projectId":"70e932c0-cb50-40f9-aba0-ced935f2d5de","name":"g0v hackath33n | 台灣零時政府第參拾參次不顧北京反對___黑客松","type":"實體活動","description":"歡迎公民、鄉民、憤青、開發者、設計者、社會運動工作者、公務員、法律專家、文字工作者、插畫家與媒體工作者等諸眾，帶著熱血來盡一己之力，開源協作參與社會。","startDate":"2019-03-09T01:00:00.000Z","endDate":"2019-03-09T10:00:00.000Z","annouceToContributors":false,"location":{"name":"中央研究院資訊科學所","address":"台北市南港區研究院路二段128號"},"link":"https://g0v-jothon.kktix.cc/events/g0v-hackath33n"},{"id":"9befb5cc-4422-42de-8d37-7cc92595d6fd","projectId":"70e932c0-cb50-40f9-aba0-ced935f2d5de","name":"g0v hackath32n | 台灣零時政府第参拾貳次蜂蜜檸檬黑客松","type":"實體活動","description":"歡迎公民、鄉民、憤青、開發者、設計者、社會運動工作者、公務員、法律專家、文字工作者、插畫家與媒體工作者等諸眾，帶著熱血來盡一己之力，開源協作參與社會。","startDate":"2018-12-08T01:00:00.000Z","endDate":"2018-12-08T10:00:00.000Z","annouceToContributors":false,"location":{"name":"中央研究院資訊科學所","address":"台北市南港區研究院路二段128號"},"link":"https://g0v-jothon.kktix.cc/events/g0v-hackath32n"},{"id":"56446c97-c92c-4583-909e-de4ba59ec015","projectId":"70e932c0-cb50-40f9-aba0-ced935f2d5de","name":"11/11 g0v 第拾參次基礎建設松","type":"實體活動","description":"g0v 第拾參次基礎建設松將於 11/11（日）14:00 舉行，歡迎自由登記提案，一起交流、開幹、喝啤酒！","startDate":"2018-11-11T05:30:00.000Z","endDate":"2018-11-11T10:00:00.000Z","annouceToContributors":false,"location":{"name":"Cymking Space","address":"台北市南港區南港路三段52號"},"link":"https://g0v-jothon.kktix.cc/events/infrath13n"},{"id":"a4d65875-5cbc-4672-8445-32ed7f3692aa","projectId":"70e932c0-cb50-40f9-aba0-ced935f2d5de","name":"9/2 g0v 第拾貳次基礎建設松","type":"實體活動","description":"g0v 第拾貳次基礎建設松將於 9/2（日）14:00 舉行，歡迎自由登記提案，一起交流、開幹、喝啤酒！","startDate":"2018-09-02T06:00:00.000Z","endDate":"2018-09-02T09:00:00.000Z","annouceToContributors":false,"location":{"name":"摩茲工寮","address":"台北市中正區八德路一段94號3樓"},"link":"https://g0v-jothon.kktix.cc/events/infrath12n"},{"id":"6ea94077-7c8d-483b-b064-65b5f97e0360","projectId":"70e932c0-cb50-40f9-aba0-ced935f2d5de","name":"g0v hackath31n | 台灣零時政府第參拾壹次香蕉吃到飽松","type":"實體活動","description":"歡迎公民、鄉民、憤青、開發者、設計者、社會運動工作者、公務員、法律專家、文字工作者、插畫家與媒體工作者等諸眾，帶著熱血來盡一己之力，開源協作參與社會。","startDate":"2018-07-07T01:00:00.000Z","endDate":"2018-07-07T10:00:00.000Z","annouceToContributors":false,"location":{"name":"中央研究院資訊科學所","address":"台北市南港區研究院路二段128號"},"link":"https://g0v-jothon.kktix.cc/events/g0v-hackath31n"},{"id":"00bc8c9b-3195-4de4-b3f4-105f8fc835ac","projectId":"70e932c0-cb50-40f9-aba0-ced935f2d5de","name":"6/19 g0v 第拾壹次基礎建設「傍晚熱炒晚上松」 ft. Frank Pasquale","type":"實體活動","description":"本次 g0v 第拾壹次基礎建設「傍晚熱炒晚上松」ft. Frank Pasquale & Ray Cha 將於 6/19（二）19:00 舉行，難得短講與交流機會，一起來 hacking 吧！","startDate":"2018-06-19T11:00:00.000Z","endDate":"2018-06-19T14:00:00.000Z","annouceToContributors":false,"location":{"name":"群島","address":"台北市中山區長安東路一段45-2號3樓"},"link":"https://g0v-jothon.kktix.cc/events/infrath11n"},{"id":"93feaa17-5d44-4de5-8071-5e648672272e","projectId":"70e932c0-cb50-40f9-aba0-ced935f2d5de","name":"g0v hackath30n | 台灣零時政府第參拾次佛系黑客松","type":"實體活動","description":"本次 g0v 大黑客松將於 5/5 舉辦，歡迎公民、鄉民、憤青、開發者、設計者、社會運動工作者、公務員、法律專家、文字工作者、插畫家與媒體工作者等諸眾，帶著熱血來盡一己之力，開源協作參與社會。","startDate":"2018-05-05T01:00:00.000Z","endDate":"2018-05-05T10:00:00.000Z","annouceToContributors":false,"location":{"name":"中央研究院資訊科學所","address":"115台北市南港區研究院路二段128號"},"link":"https://g0v-jothon.kktix.cc/events/g0v-hackath30n"},{"id":"43480dc0-d97d-46cf-8b03-99ac824b41f9","projectId":"70e932c0-cb50-40f9-aba0-ced935f2d5de","name":"g0v 復活節第拾次基礎建設松","type":"實體活動","description":"本次 g0v 基礎建設松將於 4/14（六）14:00 舉行，一起組裝 g0v 社群工具模組，促進人坑松的交流吧！","startDate":"2018-04-14T06:00:00.000Z","endDate":"2018-04-14T10:00:00.000Z","annouceToContributors":false,"location":{"name":"摩茲工寮 Mozilla Space ","address":"台北市八德路一段 94 號 3 樓"},"link":"https://g0v-jothon.kktix.cc/events/infrath10n"},{"id":"ab3a372b-7022-4a80-9022-3e8da31c933b","projectId":"70e932c0-cb50-40f9-aba0-ced935f2d5de","name":"g0v hackath29n | 台灣零時政府第貳拾玖次開放資料黑客松","type":"實體活動","description":"台灣零時政府 g0v.tw 雙月大黑客松 不只寫程式改造社會 不要問為什麼沒有人做這個，先承認你就是沒有人 本次 g0v 大黑客松將於 3/3 日 與全世界 128 個活動共同響應「世界開放資料日」 ","startDate":"2018-03-03T01:00:00.000Z","endDate":"2018-03-03T10:00:00.000Z","annouceToContributors":false,"location":{"name":"中央研究院資訊科學所","address":""},"link":"https://g0v-jothon.kktix.cc/events/g0v-hackath29n"},{"id":"7afb512a-2116-4ce6-ae37-63ca4597041e","projectId":"70e932c0-cb50-40f9-aba0-ced935f2d5de","name":"g0v hackath28n | 台灣零時政府第貳拾捌次高牆功德黑客松","type":"實體活動","description":"台灣零時政府 g0v.tw 雙月大黑客松 不只寫程式改造社會 還要有菩薩心會許願蓋高牆做功德 不要問為什麼沒有人做功德，先承認你就是沒有人 來吧！來提新專案、來做舊專案、來認識新朋友！ 拓展開源、開幹","startDate":"2018-01-13T01:00:00.000Z","endDate":"2018-01-13T10:00:00.000Z","annouceToContributors":false,"location":{"name":"中央研究院資訊科學所","address":""},"link":"https://g0v-jothon.kktix.cc/events/g0v-hackath28n"},{"id":"15933ff0-fa8d-44b3-9649-50bae547e5a8","projectId":"70e932c0-cb50-40f9-aba0-ced935f2d5de","name":"在開源社群改造社會：2018 年 g0v 公民科技創新獎助金提案說明工作坊","type":"實體活動","description":"2018 g0v 公民科技創新獎助金上線啦！1/1-1/21 線上公開提案。不知道怎麼提案嗎？不會寫程式嗎？歡迎來參加 12/27 的提案說明工作坊，一起入坑。","startDate":"2018-01-03T11:00:00.000Z","endDate":"2018-01-03T13:00:00.000Z","annouceToContributors":false,"location":{"name":"摩茲工寮 Mozilla Space","address":"台北市八德路一段 94 號 3 樓"},"link":"https://g0v-jothon.kktix.cc/events/grant-apply-worksh0p-moz"},{"id":"da998e1b-fe95-4b13-a9a7-8fcebe34366b","projectId":"70e932c0-cb50-40f9-aba0-ced935f2d5de","name":"公民團體與科技協力：從透明足跡到 g0v 獎助金（2018 年 g0v 公民科技創新獎助金提案說明工作坊）","type":"實體活動","description":"2018 g0v 公民科技創新獎助金上線啦！1/1-1/21 線上公開提案。不知道怎麼提案嗎？不會寫程式嗎？歡迎來參加 12/27 的提案說明工作坊，一起入坑。","startDate":"2017-12-27T11:00:00.000Z","endDate":"2017-12-27T13:00:00.000Z","annouceToContributors":false,"location":{"name":"綠盟辦公室","address":"台北市羅斯福路二段 70 號 8 樓之 3"},"link":"https://g0v-jothon.kktix.cc/events/grant-apply-worksh0p-gcaa"},{"id":"5e333074-8e2a-4e7a-a493-1c7ed4f0036e","projectId":"70e932c0-cb50-40f9-aba0-ced935f2d5de","name":"g0v hackath27n | 台灣零時政府全球開放立法松","type":"實體活動","description":"台灣零時政府 g0v.tw 雙月大黑客松 不只寫程式改造社會 不要問為什麼沒有人做這個，先承認你就是沒有人   \t \t\t \t\t\t \t\t\tGLOW^4 是開放政府夥伴聯盟（OGP）開放立法工作小組所舉辦","startDate":"2017-11-25T01:00:00.000Z","endDate":"2017-11-25T10:00:00.000Z","annouceToContributors":false,"location":{"name":"中央研究院資訊科學所","address":"中央研究院資訊科學所"},"link":"https://g0v-jothon.kktix.cc/events/g0v-hackath27n"},{"id":"5afa2978-f053-4cba-a7a9-52eb5c5b67df","projectId":"70e932c0-cb50-40f9-aba0-ced935f2d5de","name":"g0v 第玖次基礎建設松","type":"實體活動","description":"本次 g0v 基礎建設松將於 10/21（六）13:30 舉行，一起組裝 g0v 社群工具模組，促進人坑松的交流吧！","startDate":"2017-10-21T05:30:00.000Z","endDate":"2017-10-21T10:00:00.000Z","annouceToContributors":false,"location":{"name":"摩茲工寮 Mozilla Space ","address":"台北市八德路一段 94 號 3 樓"},"link":"https://g0v-jothon.kktix.cc/events/infrath9n"},{"id":"d5d60443-e4b8-4f35-9d19-d0f5aa9a25f3","projectId":"70e932c0-cb50-40f9-aba0-ced935f2d5de","name":"g0v hackath26n | 台灣零時政府五週年黑客松","type":"實體活動","description":"g0v 五週年啦，要擴大舉辦，一起跨界公民協作，吃吃喝喝做專案！Join g0v 5th anniversary hackathon to do cool civic tech projects. ","startDate":"2017-09-16T01:00:00.000Z","endDate":"2017-09-16T10:00:00.000Z","annouceToContributors":false,"location":{"name":"TAF 空總創新基地聯合餐廳","address":"106台北市大安區建國南路一段177號"},"link":"https://g0v-jothon.kktix.cc/events/g0v-hackath26n"},{"id":"0ff2d227-8b6b-4501-9e10-98f44b9eda83","projectId":"70e932c0-cb50-40f9-aba0-ced935f2d5de","name":"g0v 公民科技創新獎助金— 2017 春季成果發表會","type":"實體活動","description":"2017 年春季 g0v 公民科技創新獎助金獲獎專案，將在 Google 台北辦公室分享 6 個月加速開發所創造的社會改變。會後為 WCIT x Civic Tech Fest 合辦的國際交流晚會。","startDate":"2017-09-11T09:30:00.000Z","endDate":"2017-09-11T12:30:00.000Z","annouceToContributors":false,"location":{"name":"Google 台北辦公室","address":"台北市信義區信義路五段 7 號台北 101 大樓 75 樓"},"link":"https://g0v-jothon.kktix.cc/events/2017a-g0v-grant-demo"},{"id":"f61219a4-5f64-48fa-9fc8-ecb5dee8117d","projectId":"70e932c0-cb50-40f9-aba0-ced935f2d5de","name":"g0v@Bangkok hackath0n | Let's Make Some Data Open!","type":"實體活動","description":"Ask not why nobody is doing this. You are the \"nobody\"! Join the frist g0v's hackathon @ Bangkok to ","startDate":"2017-07-29T01:00:00.000Z","endDate":"2017-07-29T10:00:00.000Z","annouceToContributors":false,"location":{"name":"Room 710 (7th Floor)","address":"Mahitaladhibesra Building, Chulalongkorn University "},"link":"https://g0v-jothon.kktix.cc/events/bangkok-hackath0n"},{"id":"0ce75f03-a947-474f-a265-6c6f37b223aa","projectId":"70e932c0-cb50-40f9-aba0-ced935f2d5de","name":"g0v hackath25n | 台灣零時政府第貳拾伍次一綱多本黑客松","type":"實體活動","description":"台灣零時政府 g0v.tw 雙月大黑客松 不只寫程式改造社會 不要問為什麼沒有人做這個，先承認你就是沒有人 來吧！來提新專案、來做舊專案、來認識新朋友！ 拓展開源、開幹、開花的公民行動精神 ‣ 本活動","startDate":"2017-07-01T01:00:00.000Z","endDate":"2017-07-01T10:00:00.000Z","annouceToContributors":false,"location":{"name":"中央研究院資訊科學所","address":""},"link":"https://g0v-jothon.kktix.cc/events/g0v-hackath25n"},{"id":"44cf61c5-9627-42ec-85e9-80bab8931734","projectId":"70e932c0-cb50-40f9-aba0-ced935f2d5de","name":"2017 年秋季 g0v 公民科技創新獎助金提案說明工作坊","type":"實體活動","description":"下一期 g0v 公民科技創新獎助金即將開跑！7/1 -7/16 線上公開提案。不知道怎麼提案嗎？歡迎來參加 6/17 的提案說明工作坊，帶上你的點子和行動力，一起來挖坑。","startDate":"2017-06-17T06:00:00.000Z","endDate":"2017-06-17T09:00:00.000Z","annouceToContributors":false,"location":{"name":"摩茲工寮 Mozilla Space ","address":"台北市八德路一段 94 號 3 樓"},"link":"https://g0v-jothon.kktix.cc/events/grant-apply-worksh0p"},{"id":"5bd93eda-d498-4940-9c30-9362ec208226","projectId":"70e932c0-cb50-40f9-aba0-ced935f2d5de","name":"搶救 g0v Hackpad 松","type":"實體活動","description":"Hackpad 即將在 7/19 結束服務，需要大家一起搶救公民運動的資料！將討論如何備份g0v 眾多專案以及許多公民運動的紀錄，以及如何創造同樣友善有效的線上協作平台。","startDate":"2017-06-10T05:30:00.000Z","endDate":"2017-06-10T10:00:00.000Z","annouceToContributors":false,"location":{"name":"摩茲工寮 Mozilla Space ","address":"台北市八德路一段 94 號 3 樓"},"link":"https://g0v-jothon.kktix.cc/events/hackpadthon"},{"id":"efb645ac-350a-43d3-a67a-8363e0741afd","projectId":"70e932c0-cb50-40f9-aba0-ced935f2d5de","name":"g0v hackath24n | 台灣零時政府第貳拾肆次凍省黑客松","type":"實體活動","description":"台灣零時政府 g0v.tw 雙月大黑客松 不只寫程式改造社會 不要問為什麼沒有人做這個，先承認你就是沒有人 來吧！來提新專案、來做舊專案、來認識新朋友！ 拓展開源、開幹、開花的公民行動精神 ‣ 本活動","startDate":"2017-05-06T01:00:00.000Z","endDate":"2017-05-06T10:00:00.000Z","annouceToContributors":false,"location":{"name":"中央研究院資訊科學所","address":""},"link":"https://g0v-jothon.kktix.cc/events/g0v-hackath24n"},{"id":"28411745-ab2d-4f4c-918e-053feb1d4d56","projectId":"70e932c0-cb50-40f9-aba0-ced935f2d5de","name":"g0v 第捌次基礎建設松","type":"實體活動","description":"本次 g0v 基礎建設松將於 4/20（四）19:00 舉行，一起組裝 g0v 社群工具模組，讓更多人使用吧！","startDate":"2017-04-20T11:00:00.000Z","endDate":"2017-04-20T13:30:00.000Z","annouceToContributors":false,"location":{"name":"摩茲工寮 Mozilla Space ","address":"台北市八德路一段 94 號 3 樓"},"link":"https://g0v-jothon.kktix.cc/events/infrath8n"},{"id":"af4ef116-c7f2-4c1b-a4e8-60449bcce078","projectId":"70e932c0-cb50-40f9-aba0-ced935f2d5de","name":"g0v hackath23n | 台灣零時政府第貳拾參次開放資料黑客松","type":"實體活動","description":"本次 g0v 大黑客松將於 3/4 日舉行，並與全世界 130 個城市共同響應「世界開放資料日」！","startDate":"2017-03-04T01:00:00.000Z","endDate":"2017-03-04T10:00:00.000Z","annouceToContributors":false,"location":{"name":"中央研究院資訊科學所","address":""},"link":"https://g0v-jothon.kktix.cc/events/g0v-hackath23n"},{"id":"bf1fff2c-048f-4a79-bc6b-bdc0406fe2c7","projectId":"70e932c0-cb50-40f9-aba0-ced935f2d5de","name":"g0v 第柒次基礎建設緊急松 - 德國 Prototype Fund x g0v 獎助金 2/16","type":"實體活動","description":"德國開放知識基金會的 Eileen 在 Code For All 的交換計畫支持下，來台灣一個月在 OCF 辦公室 co-work，並將一起與社群的夥伴協作公民科技獎助金、g0v.news 等專案。我","startDate":"","endDate":"","annouceToContributors":false,"location":{"name":"摩茲工寮 Mozilla Space","address":"台北市八德路一段 94 號 3 樓"},"link":"https://g0v-jothon.kktix.cc/events/infrath7n"},{"id":"29bb1391-729d-498c-9b12-4a661c265404","projectId":"70e932c0-cb50-40f9-aba0-ced935f2d5de","name":"g0v 第陸次基礎建設「大平台」松 - 1/21","type":"實體活動","description":"g0v 社群由「人、坑、松」組成，如何讓參與者容易串連協作，需要更多好用的工具與平台。兩年前曾經召開過第零次基礎建設松，揪松團近期重啟社群基礎建設，希望持續常態經營！","startDate":"","endDate":"","annouceToContributors":false,"location":{"name":"摩茲工寮","address":"台北市八德路一段 94 號 3 樓"},"link":"https://g0v-jothon.kktix.cc/events/infrath6n"},{"id":"d19baff3-56d2-49b2-a323-1271394480e3","projectId":"70e932c0-cb50-40f9-aba0-ced935f2d5de","name":"g0v hackath22n | 台灣零時政府第貳拾貳次公民科學黑客松","type":"實體活動","description":"（本次主圖由 @tuiry 繪製 CC0 釋出，主圖說明）   2016 年即將結束 不要錯過 12/17 週六，今年度最後一次黑客松 來吧！來提新專案、來做舊專案、來認識新朋友！ 讓開源、開幹、開花","startDate":"2016-12-17T01:00:00.000Z","endDate":"2016-12-17T10:00:00.000Z","annouceToContributors":false,"location":{"name":"中央研究院資訊科學所","address":""},"link":"https://g0v-jothon.kktix.cc/events/g0v-hackath22n"},{"id":"1caa0493-1397-4343-8e99-36f6957a2179","projectId":"70e932c0-cb50-40f9-aba0-ced935f2d5de","name":"g0v hackath21n | 台灣零時政府根留台灣","type":"實體活動","description":"**本次黑客松與叡揚資訊聯名合作舉辦** 10/15 週六，第貳拾壹次根留台灣黑客松即將上場 只要開源，議題不限 歡迎大家來提新專案、接力舊專案， 讓開源、公民精神持續延燒！ 主圖 by @chiha","startDate":"2016-10-15T01:00:00.000Z","endDate":"2016-10-15T10:00:00.000Z","annouceToContributors":false,"location":{"name":"中央研究院資訊科學所","address":""},"link":"https://g0v-jothon.kktix.cc/events/g0v-hackath21n"},{"id":"3e5d7aeb-d343-4c50-bdf3-27843de70dfc","projectId":"70e932c0-cb50-40f9-aba0-ced935f2d5de","name":"g0v 第伍次基礎建設松 - 10/8","type":"實體活動","description":"g0v 社群由「人、坑、松」組成，如何讓參與者容易串連協作，需要更多好用的工具與平台。兩年前曾經召開過第零次基礎建設松，揪松團近期重啟社群基礎建設，希望持續常態經營！","startDate":"2016-10-08T02:30:00.000Z","endDate":"2016-10-08T08:00:00.000Z","annouceToContributors":false,"location":{"name":"摩茲工寮","address":"台北市八德路一段 94 號 3 樓"},"link":"https://g0v-jothon.kktix.cc/events/infrath5n"},{"id":"bd000e8b-dbbe-46f0-856c-365910f6aa56","projectId":"70e932c0-cb50-40f9-aba0-ced935f2d5de","name":"g0v 第肆次基礎建設緊急松 - Enspiral x g0v 社群發展經驗分享 8/26 ","type":"實體活動","description":"g0v 社群由「人、坑、松」組成，如何讓參與者容易串連協作，需要更多好用的工具與平台。兩年前曾經召開過第零次基礎建設松，揪松團近期重啟社群基礎建設，希望持續常態經營！","startDate":"2016-08-26T11:00:00.000Z","endDate":"2016-08-26T13:40:00.000Z","annouceToContributors":false,"location":{"name":"Gary&Emerson;_Space （近中山國中站）","address":"台北市中山區復興北路 350 號 3 樓"},"link":"https://g0v-jothon.kktix.cc/events/infrath4n"},{"id":"b457de56-1df8-40ea-bf2b-ec75d21a4811","projectId":"70e932c0-cb50-40f9-aba0-ced935f2d5de","name":"g0v hackath20n | 台灣零時政府第貳拾次總統直選黑客松","type":"實體活動","description":"一例一休勞基法爭議、血汗旅遊業.......議題好多，公民好忙!想做些甚麼，帶來改變嗎？快來跟大家一起挖坑與入坑吧!不要錯過 8/6 週六，第貳拾次總統直選黑客松你有許多想法嗎？想找夥伴實現嗎？別猶豫，快來 g0v 黑客松!只要開源，議題不限歡迎大家來提新專案、接力舊專案，讓開源、公民精神持續延燒。8/6，等你  一  同 開  幹。","startDate":"2016-08-06T01:00:00.000Z","endDate":"2016-08-06T10:00:00.000Z","annouceToContributors":false,"location":{"name":"中央研究院資訊科學所","address":"台北市南港區研究院路二段128號"},"link":"https://g0v-jothon.kktix.cc/events/g0v-hackath20n"},{"id":"052fe2ef-059b-4d84-a6f3-f89a0ad2fd3b","projectId":"70e932c0-cb50-40f9-aba0-ced935f2d5de","name":"g0v 第參次基礎建設閃電松 - 7/23","type":"實體活動","description":"g0v 社群由「人、坑、松」組成，如何讓參與者容易串連協作，需要更多好用的工具與平台。兩年前曾經召開過第零次基礎建設松，揪松團近期重啟社群基礎建設，希望持續常態經營！","startDate":"2016-07-23T05:30:00.000Z","endDate":"2016-07-23T09:00:00.000Z","annouceToContributors":false,"location":{"name":"摩茲工寮","address":"台北市八德路一段 94 號 3 樓"},"link":"https://g0v-jothon.kktix.cc/events/infrath3n"},{"id":"9c0e3a6c-de33-4691-8852-de9c1f5c6787","projectId":"70e932c0-cb50-40f9-aba0-ced935f2d5de","name":"g0v 第貳次基礎建設黑客松 - 7/3","type":"實體活動","description":"g0v 社群由「人、坑、松」組成，如何讓參與者容易串連協作，需要更多好用的工具與平台。兩年前曾經召開過第零次基礎建設松，揪松團近期重啟社群基礎建設，希望持續常態經營！","startDate":"2016-07-03T02:30:00.000Z","endDate":"2016-07-03T09:00:00.000Z","annouceToContributors":false,"location":{"name":"摩茲工寮","address":"台北市八德路一段 94 號 3 樓"},"link":"https://g0v-jothon.kktix.cc/events/infrath2n"},{"id":"23206aac-29ce-46bb-82bf-9319129d769a","projectId":"70e932c0-cb50-40f9-aba0-ced935f2d5de","name":"g0v hackath19n | 台灣零時政府第拾玖次飛彈試射黑客松","type":"實體活動","description":"g0v Summit 2016 年會結束後是不是有滿滿強烈挖坑、填坑的動力呢？不要錯過 6/18 週六，第拾玖次飛彈試射黑客松來吧！來提新專案、來做舊專案、來認識新朋友！讓開源、開幹、開花的公民行動精神繼續延燒。","startDate":"2016-06-18T01:00:00.000Z","endDate":"2016-06-18T10:00:00.000Z","annouceToContributors":false,"location":{"name":"中央研究院資訊科學所","address":"台北市南港區研究院路二段128號"},"link":"https://g0v-jothon.kktix.cc/events/g0v-hackath19n"},{"id":"a941ca7a-1b3a-4293-b6af-3dc3e44981ba","projectId":"70e932c0-cb50-40f9-aba0-ced935f2d5de","name":"g0v 第壹次基礎建設黑客松 - 6/12","type":"實體活動","description":"g0v 社群由「人、坑、松」組成，如何讓參與者容易串連協作，需要更多好用的工具與平台。兩年前曾經召開過第零次基礎建設松，揪松團近期重啟社群基礎建設，希望持續常態經營！","startDate":"2016-06-12T02:30:00.000Z","endDate":"2016-06-12T09:30:00.000Z","annouceToContributors":false,"location":{"name":"OCF 辦公室（摩茲工寮樓上）","address":"台北市八德路一段 94 號 4 樓"},"link":"https://g0v-jothon.kktix.cc/events/infrath1n"},{"id":"2424af91-0265-44dc-8cb0-5166e9d03a09","projectId":"70e932c0-cb50-40f9-aba0-ced935f2d5de","name":"g0v hackath18n | 台灣零時政府第拾捌次亞太營運黑客松","type":"實體活動","description":"大選剛過，新局將啟以開源實作精神關注公共議題的 g0v 黑客松依舊持續上場！本次黑客松與國際 Open Data Day 同步開跑來吧！來提新專案、來做舊專案、來認識新朋友讓開源、開幹、開花的公民行動精神繼續延燒！","startDate":"2016-03-05T01:00:00.000Z","endDate":"2016-03-05T10:00:00.000Z","annouceToContributors":false,"location":{"name":"中央研究院資訊科學所","address":"台北市南港區研究院路二段128號"},"link":"https://g0v-jothon.kktix.cc/events/g0v-hackath18n"},{"id":"fd043aa5-bc2f-45ce-a2af-ac9c8e2610ad","projectId":"70e932c0-cb50-40f9-aba0-ced935f2d5de","name":"g0v hackath17n | 台灣零時政府第拾柒次立委改選黑客松","type":"實體活動","description":"從 2012 年底開始，g0v 社群持續舉辦每兩個月一次百人黑客松，提供推動資訊透明、開放參與的公民協作平台，大家一起吃了很多披薩炸雞，同時催生多項專案。開放政府、太陽花運動、社會議題都有 g0v 貢獻者的身影。","startDate":"2015-12-26T01:00:00.000Z","endDate":"2015-12-26T10:00:00.000Z","annouceToContributors":false,"location":{"name":"中央研究院資訊科學所","address":"台北市南港區研究院路二段128號"},"link":"https://g0v-jothon.kktix.cc/events/g0v-hackath17n"},{"id":"41791b64-aeec-49f0-9193-3c8099d70bc8","projectId":"70e932c0-cb50-40f9-aba0-ced935f2d5de","name":"g0v hackath16n | 第拾陸次刑法一百黑客松","type":"實體活動","description":"從 2012 年底開始，g0v 社群持續舉辦每兩個月一次百人黑客松，提供推動資訊透明、開放參與的公民協作平台，大家一起吃了很多披薩炸雞，同時催生多項專案。開放政府、太陽花運動、社會議題都有 g0v 貢獻者的身影。","startDate":"2015-10-24T01:00:00.000Z","endDate":"2015-10-24T10:00:00.000Z","annouceToContributors":false,"location":{"name":"中央研究院資訊科學所","address":"台北市南港區研究院路二段128號"},"link":"https://g0v-jothon.kktix.cc/events/g0v-hackath16n"},{"id":"cc095081-4646-473a-bcff-c66582f05690","projectId":"70e932c0-cb50-40f9-aba0-ced935f2d5de","name":"g0v.tw hackath15n | 台灣零時政府第拾伍次資料科學黑客松","type":"實體活動","description":"從 2012 年底開始，g0v 社群持續舉辦每兩個月一次百人黑客松，提供推動資訊透明、開放參與的公民協作平台，大家一起吃了很多披薩炸雞，同時催生多項專案。開放政府、太陽花運動、社會議題都有 g0v 貢獻者的身影。","startDate":"2015-08-22T01:00:00.000Z","endDate":"2015-08-23T09:00:00.000Z","annouceToContributors":false,"location":{"name":"中央研究院人文社會科學館","address":"台北市南港區研究院路二段128號"},"link":"https://g0v-jothon.kktix.cc/events/g0v-hackath15n"},{"id":"48b4092f-f269-4a9d-a2e0-41127fa6b520","projectId":"70e932c0-cb50-40f9-aba0-ced935f2d5de","name":"g0v.tw hackath14n | 台灣零時政府第拾肆次野百合黑客松","type":"實體活動","description":"從一開始資料爬梳、資訊人為主，到現在已經演化出更多不同的類型：有公部門的參與、與 NGO 深度的協作，當然還有宅宅的投入與開源社群持續耕耘「開放」不是一時的口號，而是需要長期投入的社會參與。每一次爆發力都需要平時的鴨子滑水耕耘，大松是進度衝刺的好時機！來吧！來提新專案、來做舊專案、來認識新朋友，動動腦也吃炸雞！讓開源、開幹、開花的公民行動精神繼續延燒。","startDate":"2015-06-13T01:00:00.000Z","endDate":"2015-06-13T10:00:00.000Z","annouceToContributors":false,"location":{"name":"中央研究院資訊科學所","address":"台北市南港區研究院路二段128號"},"link":"https://g0v-jothon.kktix.cc/events/g0v-hackath14n"},{"id":"59cd73bd-9727-4b91-b883-01e61c35a6f4","projectId":"70e932c0-cb50-40f9-aba0-ced935f2d5de","name":"g0v.tw hackath13n | 台灣零時政府第拾參次無殼蝸牛黑客松","type":"實體活動","description":"從一開始資料爬梳、資訊人為主，到現在已經演化出更多不同的類型：有公部門的參與、與 NGO 深度的協作，當然還有宅宅的投入與開源社群持續耕耘「開放」不是一時的口號，而是需要長期投入的社會參與。每一次爆發力都需要平時的鴨子滑水耕耘，大松是進度衝刺的好時機！來吧！來提新專案、來做舊專案、來認識新朋友，動動腦也吃炸雞！讓開源、開幹、開花的公民行動精神繼續延燒。","startDate":"2015-04-18T01:00:00.000Z","endDate":"2015-04-18T10:00:00.000Z","annouceToContributors":false,"location":{"name":"中央研究院資訊科學所","address":"台北市南港區研究院路二段128號"},"link":"https://g0v-jothon.kktix.cc/events/g0v-hackath13n"},{"id":"2e366e67-e3cb-4deb-b33a-e4f6c320abcd","projectId":"70e932c0-cb50-40f9-aba0-ced935f2d5de","name":"g0v Hackath39n | 台灣零時政府第參拾玖次又在家黑客松 Stay Home","type":"線上活動","description":"從一開始資料爬梳、資訊人為主，到現在已經演化出更多不同的類型：有公部門的參與、與 NGO 深度的協作，當然還有宅宅的投入與開源社群持續耕耘「開放」不是一時的口號，而是需要長期投入的社會參與。每一次爆發力都需要平時的鴨子滑水耕耘，大松是進度衝刺的好時機！來吧！來提新專案、來做舊專案、來認識新朋友，動動腦也吃炸雞！讓開源、開幹、開花的公民行動精神繼續延燒。","startDate":"2020-05-23T01:00:00.000Z","endDate":"2020-05-23T10:00:00.000Z","annouceToContributors":false,"guestLimit":1000,"attendanceCount":103,"location":{"name":"Online Event","address":""},"link":"https://meet.jothon.online/event/show/g0v-hackath39n"},{"id":"6c7caed6-6273-4f87-9a29-121900995d62","projectId":"70e932c0-cb50-40f9-aba0-ced935f2d5de","name":"g0v summit 2014 檢討^H^H回味松","type":"實體活動","description":"啥米零時政府已經結束大半年，但還沒檢討回味松，summit 2016 版也逐漸醞釀中，讓我們來個回味共筆松，也把經驗交接給下屆工頭們吧～ 時間地點： 2015/05/2 11:00-17:00 摩茲工","startDate":"2015-05-02T03:00:00.000Z","endDate":"2015-05-02T09:00:00.000Z","annouceToContributors":false,"location":{"name":"摩茲工寮","address":"100台北市中正區八德路一段94號3F"},"link":"https://g0v-tw.kktix.cc/events/summithon"},{"id":"dd9ec1c7-8262-42f6-ae58-9184220a4b63","projectId":"70e932c0-cb50-40f9-aba0-ced935f2d5de","name":"3/28 第九次萌典松 moed9ct","type":"實體活動","description":"【主題】固定於單月底舉辦的 g0v 零時政府中型黑客松，三月於 3/28 舉辦。 【同場舉行】 ... 松松相連募集中，歡迎到 Hackpad 頁面填寫。 【共筆】請見 Hackpad 頁面 及 活動","startDate":"2015-03-28T03:00:00.000Z","endDate":"2015-03-28T13:00:00.000Z","annouceToContributors":false,"location":{"name":"BOOKSHOW 說書會","address":"台北市信義區基隆路一段141號6樓之7"},"link":"https://g0v-tw.kktix.cc/events/moedict-3-28"},{"id":"75d80303-a0be-41c5-bc1a-2219fcda0144","projectId":"70e932c0-cb50-40f9-aba0-ced935f2d5de","name":"g0v.tw hackath12n | 台灣零時政府第拾貳次不得宣傳罷免黑客松","type":"實體活動","description":"☞ 為何要來 來提新專案、來作舊專案、來認識新朋友，動動腦也吃炸雞！讓開源、開幹、開花的公民行動精神在新的一年繼續延燒。 2/14 是情人節，歡迎有情人作伙來 hacking。當天也是台灣二十年來首次","startDate":"2015-02-14T01:00:00.000Z","endDate":"2015-02-14T10:00:00.000Z","annouceToContributors":false,"location":{"name":"中央研究院資訊科學所 ","address":"台北市南港區研究院路二段128號"},"link":"https://g0v-tw.kktix.cc/events/g0v-hackath12n"},{"id":"0c90f048-db3a-4feb-87f4-058af1257372","projectId":"70e932c0-cb50-40f9-aba0-ced935f2d5de","name":"1/18 第八次萌典松 moed8ct","type":"實體活動","description":"【主題】固定於單月底舉辦的 g0v 零時政府中型黑客松，一月於 1/18 舉辦。 【同場舉行】 ... 松松相連募集中，歡迎到 Hackpad 頁面填寫。 【共筆】請見 Hackpad 頁面 及 活動","startDate":"2015-01-18T03:00:00.000Z","endDate":"2015-01-18T13:00:00.000Z","annouceToContributors":false,"location":{"name":"BOOKSHOW 說書會","address":"台北市信義區基隆路一段141號6樓之7"},"link":"https://g0v-tw.kktix.cc/events/moedict-1-18"},{"id":"4bd4f6e8-1c7c-487f-8365-541c6c70f4a2","projectId":"70e932c0-cb50-40f9-aba0-ced935f2d5de","name":"g0v.tw hackath11n | 台灣零時政府第拾壹次開放報禁黑客松","type":"實體活動","description":"☞ 為何要來 從 2012 年底的第零次動員戡亂黑客松開始，雙月一次的百人 g0v 黑客松，竟也已連續辦了兩年。今年，g0v 社群鴨子划水的協作成果逐漸浮出水面。從年初與國際串連，到 318 學運","startDate":"2014-12-20T01:00:00.000Z","endDate":"2014-12-20T10:00:00.000Z","annouceToContributors":false,"location":{"name":"中央研究院資訊科學所 ","address":"台北市南港區研究院路二段128號"},"link":"https://g0v-tw.kktix.cc/events/g0v-hackath11n"},{"id":"b34dd92c-731e-4489-8ed3-d9fd6e59ea4b","projectId":"70e932c0-cb50-40f9-aba0-ced935f2d5de","name":"11/22 第七次萌典松 moed7ct","type":"實體活動","description":"【主題】固定於單月底舉辦的 g0v 零時政府中型黑客松，十一月於 11/22 舉辦。 【同場舉行】 農域松、gxv 關係松、M Project、ig0v... 松松相連募集中，歡迎到 Hackpad","startDate":"2014-11-22T03:00:00.000Z","endDate":"2014-11-22T13:00:00.000Z","annouceToContributors":false,"location":{"name":"BOOKSHOW 說書會","address":"台北市信義區基隆路一段141號6樓之7"},"link":"https://g0v-tw.kktix.cc/events/moedict-11-22"},{"id":"9b40cc2a-b992-4a49-92bc-94c5f9697ed3","projectId":"70e932c0-cb50-40f9-aba0-ced935f2d5de","name":"11/9 g0v Summit Unconference 開放工作坊","type":"實體活動","description":"g0v Summit 第二天「開放工作坊」 ☞  Unconference  時間：2014/11/9 0900-1800 地點：中央研究院 資訊科學研究所 議程：http://summit.g0","startDate":"2014-11-09T01:00:00.000Z","endDate":"2014-11-09T10:00:00.000Z","annouceToContributors":false,"location":{"name":"中央研究院人資訊科學研究所  (Institution of Information Science of Academia Sinica)","address":"台北市南港區研究院路二段128號 (No.128, Sec. 2, Academia Rd., Nangang Dist., Taipei City 115, Taiwan)"},"link":"https://g0v-tw.kktix.cc/events/g0v-summit-2014-unconf"},{"id":"6261a0f4-1d40-4e00-97d0-f0e5e33ac22a","projectId":"70e932c0-cb50-40f9-aba0-ced935f2d5de","name":"g0v Summit 2014 - Conference - VIP and Early Bird","type":"實體活動","description":"此為【VIP貴賓】、【國際早鳥票】與【政府邀請票】的報名頁面 This page is for VIP invite code, International Early Bird and gov","startDate":"2014-11-08T01:00:00.000Z","endDate":"2014-11-08T09:00:00.000Z","annouceToContributors":false,"location":{"name":"中央研究院人文社會科學館 (HSS Bldg. of Academia Sinica)","address":"台北市南港區研究院路二段128號 (No.128, Sec. 2, Academia Rd., Nangang Dist., Taipei City 115, Taiwan)"},"link":"https://g0v-tw.kktix.cc/events/g0v-summit-2014-con-vip"},{"id":"98446fb1-0b35-4226-8f49-e229457f5d8d","projectId":"70e932c0-cb50-40f9-aba0-ced935f2d5de","name":"g0v Summit 2014 - Conference - Contributor and Normal","type":"實體活動","description":"※ 此為【g0v貢獻者】與【一般票】的 Conference 報名頁面 This page is for registering with Contributor invite code and","startDate":"2014-11-08T01:00:00.000Z","endDate":"2014-11-08T09:00:00.000Z","annouceToContributors":false,"location":{"name":"中央研究院人文社會科學館 (HSS Bldg. of Academia Sinica)","address":"台北市南港區研究院路二段128號 (No.128, Sec. 2, Academia Rd., Nangang Dist., Taipei City 115, Taiwan)"},"link":"https://g0v-tw.kktix.cc/events/g0v-summit-2014-con-nor"},{"id":"b92bb46e-1c7b-4607-ba3d-f8f297296ed9","projectId":"70e932c0-cb50-40f9-aba0-ced935f2d5de","name":"9/20 第六次萌典松 moed6ct","type":"實體活動","description":"【主題】固定於單月底舉辦的 g0v 零時政府中型黑客松，九月於 9/20 舉辦。 【同場舉行】 松松相連募集中，歡迎到 Hackpad 頁面填寫。 【共筆】請見 Hackpad 頁面。 請注意，這不是","startDate":"2014-09-20T03:00:00.000Z","endDate":"2014-09-20T13:00:00.000Z","annouceToContributors":false,"location":{"name":"BOOKSHOW 說書會","address":"台北市信義區基隆路一段141號6樓之7"},"link":"https://g0v-tw.kktix.cc/events/moedict-9-20"},{"id":"fd5263fe-6bc9-4ab3-9d3f-ce4f7e6e4653","projectId":"70e932c0-cb50-40f9-aba0-ced935f2d5de","name":"g0v Summit 2014 - Call for talks","type":"實體活動","description":"首屆 g0v 年會將在 2014 年 11 月 8 日，於台北中央研究院召開。 g0v 社群運作近兩年了，從一開始，g0v 零時政府社群便以數位世代的思維，以開源方式號召群眾參與著手開發新工具、新組織","startDate":"2014-08-31T15:50:00.000Z","endDate":"2014-08-31T15:59:00.000Z","annouceToContributors":false,"location":{"name":"Academia Sinica, Taipei, Taiwan","address":"Academia Sinica, Taipei, Taiwan"},"link":"https://g0v-tw.kktix.cc/events/g0v-summit-2014-talks"},{"id":"1e5ee986-9649-4c50-9a21-15791a208fae","projectId":"70e932c0-cb50-40f9-aba0-ced935f2d5de","name":"8/16 零時前端教學松","type":"實體活動","description":"【主題】2014年8月第三次的零時前端教學松 【課程共筆】請見 Hackfoldr 2.0 頁面。 請注意，這是變相的填坑教學松，單純想學技術的人請慎入。 學生應具備基礎：了解js的變數宣告、迴圈及流","startDate":"2014-08-16T05:30:00.000Z","endDate":"2014-08-16T09:00:00.000Z","annouceToContributors":false,"location":{"name":"BOOKSHOW 說書會","address":"台北市信義區基隆路一段141號6樓之7"},"link":"https://g0v-tw.kktix.cc/events/fr0ntend-br3dge"},{"id":"4c5b477b-4365-4318-9044-191ce7d4f79c","projectId":"70e932c0-cb50-40f9-aba0-ced935f2d5de","name":"8/2 第五次萌典松 moed5ct","type":"實體活動","description":"【主題】固定於單月底舉辦的 g0v 零時政府中型黑客松，七月底延至 8/2 舉辦。 【同場舉行】 議員松 (johnny)、農域松 (a0kman)、自表松 (Johnson)、智財松 (nchild","startDate":"2014-08-02T03:00:00.000Z","endDate":"2014-08-02T13:00:00.000Z","annouceToContributors":false,"location":{"name":"BOOKSHOW 說書會","address":"台北市信義區基隆路一段141號6樓之7"},"link":"https://g0v-tw.kktix.cc/events/moedict-8-2"},{"id":"af561c6b-8504-4ede-862e-f9f78bcd390b","projectId":"70e932c0-cb50-40f9-aba0-ced935f2d5de","name":"g0v.tw hackath9n | 台灣零時政府第玖次還我土地黑客松","type":"實體活動","description":"☞ 為何要來 g0v.tw 每兩個月一回合黑客松，打造各式資訊透明化平台，從資料透明開始，用科技工具與開源協作參與社會。 ☞ 來者何人 歡迎開發者、設計者、社會運動工作者、法律專家、文字工作者、插","startDate":"2014-06-21T01:00:00.000Z","endDate":"2014-06-21T10:00:00.000Z","annouceToContributors":false,"location":{"name":"中央研究院資訊科學所","address":"台北市南港區研究院路二段128號"},"link":"https://g0v-tw.kktix.cc/events/g0v-hackath9n"},{"id":"eb14fcfc-11c1-4ac4-8318-e92b8d45466d","projectId":"70e932c0-cb50-40f9-aba0-ced935f2d5de","name":"5/25 第四次萌典松 moed4ct","type":"實體活動","description":"【主題】固定於單月底舉辦的 g0v 零時政府中型黑客松，五月舉辦 5/25 一場。 【同場舉行】 農域松 (a0kman)、自經松 (weihung)、動民主家族松 (ETBlue)、政獻松 (ven","startDate":"2014-05-25T03:00:00.000Z","endDate":"2014-05-25T13:00:00.000Z","annouceToContributors":false,"location":{"name":"BOOKSHOW 說書會","address":"台北市信義區基隆路一段141號6樓之7"},"link":"https://g0v-tw.kktix.cc/events/moedict-5-25"},{"id":"5833ddc0-df52-4a85-a49b-25f18bef934d","projectId":"70e932c0-cb50-40f9-aba0-ced935f2d5de","name":"5/13 基礎建設迷你松","type":"實體活動","description":"hackpad 前言 二次謝頓危機後，社群基礎建設百廢待興，希望大家一起 brainstorm 一下目前的 priority，然後在十一月 summit 前集中火力解決一些問題。 形式 暫不開幹。每個","startDate":"2014-05-13T11:00:00.000Z","endDate":"2014-05-13T14:00:00.000Z","annouceToContributors":false,"location":{"name":"和多星際總部遺址","address":"忠孝東路四段170巷17弄12號"},"link":"https://g0v-tw.kktix.cc/events/g0v-infrath0n"},{"id":"ed44a129-234d-409d-856f-cd52826dfcb1","projectId":"70e932c0-cb50-40f9-aba0-ced935f2d5de","name":"g0v.tw hackath8n | 台灣零時政府第捌次解除戒嚴黑客松","type":"實體活動","description":"【請注意，本次活動場地變更為「華山1914文創園區 中3拱廳」，並增開 25 張票，於 4/16 18:00 開放增額報名】   ☞ 為何要來 g0v.tw 每兩個月一回合黑客松，打造各式資訊透明化平","startDate":"2014-04-19T01:00:00.000Z","endDate":"2014-04-19T10:00:00.000Z","annouceToContributors":false,"location":{"name":"華山1914文化創意產業園區 中3拱廳","address":"台灣台北市中正區八德路一段1號"},"link":"https://g0v-tw.kktix.cc/events/g0v-hackath8n"},{"id":"81bd4eac-2525-4c70-953d-5e6bb2573b95","projectId":"70e932c0-cb50-40f9-aba0-ced935f2d5de","name":"3/29 第三次萌典松 moed3ct","type":"實體活動","description":"這是 3/29 場次。如果想報名 3/22 場次，請按這裡。 【主題】固定於單月底舉辦的 g0v 零時政府中型黑客松，三月共有 3/22、3/29 兩場，這是第二場。 【同場舉行】 農域松 (a0km","startDate":"2014-03-29T03:00:00.000Z","endDate":"2014-03-29T13:00:00.000Z","annouceToContributors":false,"location":{"name":"BOOKSHOW 說書會","address":"台北市信義區基隆路一段141號6樓之7"},"link":"https://g0v-tw.kktix.cc/events/moedict-3-29"},{"id":"dd806373-e074-4712-a71f-d1d069f59fa4","projectId":"70e932c0-cb50-40f9-aba0-ced935f2d5de","name":"3/22 第二次萌典松 moed2ct","type":"實體活動","description":"這是 3/22 場次，歡迎報名！ 【主題】固定於單月底舉辦的 g0v 零時政府中型黑客松，三月共有 3/22、3/29 兩場，這是第一場。 【同場舉行】 直播松 (bropheus)、廣場松(ETBl","startDate":"2014-03-22T03:00:00.000Z","endDate":"2014-03-22T13:00:00.000Z","annouceToContributors":false,"location":{"name":"BOOKSHOW 說書會","address":"台北市信義區基隆路一段141號6樓之7"},"link":"https://g0v-tw.kktix.cc/events/moedict-3-22"},{"id":"741d76ab-c1a4-4642-a5a7-19ee2933ee35","projectId":"70e932c0-cb50-40f9-aba0-ced935f2d5de","name":"3/8 線路松","type":"實體活動","description":"來者何人 \t手上有閒置的網路設備的人（需要設備見 hackpad） \t對網路管理有興趣 \t想把開源協作精神推廣出去，讓台灣的公民行動能夠累積共用的知識和資源 活動內容 詳情請見 線路松 Hackpad","startDate":"2014-03-08T03:00:00.000Z","endDate":"2014-03-08T13:30:00.000Z","annouceToContributors":false,"location":{"name":"2014 臺北廢核遊行媒體區","address":"台灣台北市中正區凱達格蘭大道1號"},"link":"https://g0v-tw.kktix.cc/events/router-3-8"},{"id":"207c2707-7c7f-42ae-b65c-1caeca3f16e6","projectId":"70e932c0-cb50-40f9-aba0-ced935f2d5de","name":"g0v.tw hackath7n | 台灣零時政府第柒次自由時代黑客松","type":"實體活動","description":"共100名額，現在陸續有人取消釋出票券囉。遠端也可以透過網路聊天室參與：http://hack.g0v.tw/irc  :) ☞ 為何要來 g0v.tw 每兩個月一回合黑客松，打造各式資訊透明化平台[","startDate":"2014-02-22T01:00:00.000Z","endDate":"2014-02-22T10:00:00.000Z","annouceToContributors":false,"location":{"name":"中研院資訊科學研究所","address":"台北市南港區研究院路二段128號"},"link":"https://g0v-tw.kktix.cc/events/g0v-hackath7n"},{"id":"21a01800-41f6-4f4c-a21f-5fcb7105cc68","projectId":"70e932c0-cb50-40f9-aba0-ced935f2d5de","name":"g0v.tw 立院組小松","type":"實體活動","description":"立院組小松 時間：1/20 14:00 - 20:50 協作共筆： https://g0v.hackpad.com/KJrp3C7RusA","startDate":"2014-01-20T06:00:00.000Z","endDate":"2014-01-20T12:50:00.000Z","annouceToContributors":false,"location":{"name":"前和多星際總部","address":"台北市忠孝東路四段170巷17弄12號2F"},"link":"https://g0v-tw.kktix.cc/events/g0vly-hackathon-2"},{"id":"8f17dc82-41b8-4668-a697-37a9759b327f","projectId":"70e932c0-cb50-40f9-aba0-ced935f2d5de","name":"g0v 2014 新年松","type":"實體活動","description":"【主題】在 g0v 歡慶週歲的一年之初，來個輕鬆的聯誼交流、回顧展望： 專案回顧、實作甘苦談 口述歷史、來年展望 新手教學、初心小講 混熟臉孔、好奇問答、各言爾志、促膝長談...... 與原訂於同一天","startDate":"2014-01-04T05:00:00.000Z","endDate":"2014-01-04T15:00:00.000Z","annouceToContributors":false,"location":{"name":"BOOKSHOW 說書會","address":"台北市信義區基隆路一段141號6樓之7"},"link":"https://g0v-tw.kktix.cc/events/g0v-newyear2014"},{"id":"f0c6bde8-41db-4fe0-9da4-bd8076a07197","projectId":"70e932c0-cb50-40f9-aba0-ced935f2d5de","name":"g0v.tw hackath6n | 台灣零時政府第陸次勞動基準黑客松","type":"實體活動","description":"【為何要來】g0v.tw 滿一週年了！一年來大家從零開始，打造各式資訊透明化平台[1]，在實作串連、挖坑填坑的過程中，也凝聚出新的參與社會的模式。除了生氣翻桌，真的有太多事可以作，黑客松就是能量反應爐","startDate":"2013-12-21T01:00:00.000Z","endDate":"2013-12-21T10:00:00.000Z","annouceToContributors":false,"location":{"name":"中研院資訊科學研究所","address":"台北市南港區研究院路二段128號"},"link":"https://g0v-tw.kktix.cc/events/g0v-hackath6n"},{"id":"3d3660b3-1a6e-4368-ba99-bc6ea0d12e41","projectId":"70e932c0-cb50-40f9-aba0-ced935f2d5de","name":"g0v.tw 萌典松","type":"實體活動","description":"為慶祝 g0v.tw 萌典啄木鳥活動順利完成，加上第伍次美麗島黑客松時留下許多待辦事項，特舉行此次小松以加速進行。 【來者何人】 萌典的使用者、推廣者、測試者、開發者，以及對 g0v.tw 零時政府專","startDate":"2013-11-23T03:00:00.000Z","endDate":"2013-11-23T12:00:00.000Z","annouceToContributors":false,"location":{"name":"睡不著咖啡館","address":"台北市大安區泰順街60巷8號B1"},"link":"https://g0v-tw.kktix.cc/events/moedict"},{"id":"bdbda52c-c741-417c-88df-ff56167ab596","projectId":"70e932c0-cb50-40f9-aba0-ced935f2d5de","name":"g0v.tw 立院組小松","type":"實體活動","description":"g0v立院組經過一年的醞釀終於大爆發週日來加速進行一下吧！時間：11/10 12:00-18:00 （請吃飽再來喔） 共筆：https://g0v.hackpad.com/1110--KJrp3C7R","startDate":"2013-11-10T04:00:00.000Z","endDate":"2013-11-10T10:00:00.000Z","annouceToContributors":false,"location":{"name":"前和多星際總部","address":"台北市忠孝東路四段170巷17弄12號2F"},"link":"https://g0v-tw.kktix.cc/events/g0vly-hackathon-1"},{"id":"601326ff-cff1-47d4-b6cf-57c73e73320f","projectId":"70e932c0-cb50-40f9-aba0-ced935f2d5de","name":"g0v.tw hackath5n | 台灣零時政府第伍次美麗島黑客松","type":"實體活動","description":"【源碼大明神香油票】   應無法現場參與但希望貢獻的朋友期待，本期開放香油票12張（三張已由「政大開放資料與社群協力創新計畫」包辦），每張 2,000 元，將募集 24,000 元作為下期黑客松餐","startDate":"2013-10-20T01:00:00.000Z","endDate":"2013-10-20T10:00:00.000Z","annouceToContributors":false,"location":{"name":"中研院資訊科學研究所","address":"台北市南港區研究院路二段128號"},"link":"https://g0v-tw.kktix.cc/events/g0v-hackath5n-taipei"},{"id":"d127308f-eddc-4e75-8e0a-c4ceee6e490c","projectId":"70e932c0-cb50-40f9-aba0-ced935f2d5de","name":"g0v 雙十 hackathon","type":"實體活動","description":"十月十，上街頭，上完街頭黑客松。（上街就各自糾囉）時間：13:30-18:00 歡迎老朋友、新朋友來混一下。要提新專案可以來吸收一下 0 氣，要衝舊專案的就 BJ4 了。 活動共筆（沿用上次&上上次）","startDate":"2013-10-10T05:30:00.000Z","endDate":"2013-10-10T10:00:00.000Z","annouceToContributors":false,"location":{"name":"和多聯合辦公室","address":" 台北市大安區忠孝東路四段170巷17弄12號2樓"},"link":"https://g0v-tw.kktix.cc/events/doubleten-hackathon"},{"id":"b6e8592e-4ace-4860-8699-cad6ac9a3f88","projectId":"70e932c0-cb50-40f9-aba0-ced935f2d5de","name":"g0v.tw g0v 台南小吃松","type":"實體活動","description":"大家好，我是雨蒼。這次從上海回來台南想要辦個黑客松，做點事情，順便和大家見見面。目前活動是選用成大的教室來寫程式，活動進行時會買小吃回來給各位吃。希望有人可以先寫好小吃點單系統XD 會買的小吃預計有：","startDate":"2013-10-05T02:00:00.000Z","endDate":"2013-10-05T09:00:00.000Z","annouceToContributors":false,"location":{"name":"成大資工系4202教室","address":"台南市大學路一號(成功校區)"},"link":"https://g0v-tw.kktix.cc/events/g0v-tainan"},{"id":"d54855cd-c167-4868-9618-f417e4cf22b6","projectId":"70e932c0-cb50-40f9-aba0-ced935f2d5de","name":"g0v emergency hackathon + Federico Pistono","type":"實體活動","description":"時間：19:00~22:00 邀請到來 TEDxTaipei 的講者 Frederico Pistono 來聊天，順便黑客松 （請大家吃過飯再過來，因為有義大利人，吃 pizza 的話太弱了 XD）","startDate":"2013-10-01T11:00:00.000Z","endDate":"2013-10-01T14:00:00.000Z","annouceToContributors":false,"location":{"name":"和多聯合辦公室","address":" 台北市大安區忠孝東路四段170巷17弄12號2樓"},"link":"https://g0v-tw.kktix.cc/events/emergency-hackathon-federico"},{"id":"15efe122-4ee9-43f0-82dd-9437fe9b1ae5","projectId":"70e932c0-cb50-40f9-aba0-ced935f2d5de","name":"g0v pre-hackath5n 秋天松","type":"實體活動","description":"最近各組工作坊不少，但好久沒有小黑客松了。來聚聚一起做點什麼吧！（19:00會有pizza，直接來邊吃邊松吧。素食者請到以下共筆簽名） 活動共筆：https://g0v.hackpad.com/g0v","startDate":"2013-09-24T10:30:00.000Z","endDate":"2013-09-24T14:00:00.000Z","annouceToContributors":false,"location":{"name":"和多聯合辦公室","address":" 台北市大安區忠孝東路四段170巷17弄12號2樓"},"link":"https://g0v-tw.kktix.cc/events/g0v-pre-hackath5n"},{"id":"07263ab4-33d1-4e71-9a7b-1cecd08eb0b5","projectId":"70e932c0-cb50-40f9-aba0-ced935f2d5de","name":"g0v.tw hackath4n | 台灣零時政府第肆次國民大會黑客松","type":"實體活動","description":"【最新消息】【國民大會增額票】由於報名踴躍，我們決定稍微修改開場流程以容納更多熱血朋友！增額票 30 名將於 8/7 (三) 中午 12:00 開放！  【為何要來】g0v.tw 是一個致力於打造資訊","startDate":"2013-08-10T01:00:00.000Z","endDate":"2013-08-10T10:00:00.000Z","annouceToContributors":false,"location":{"name":"中研院資訊科學研究所","address":"台北市南港區研究院路二段128號"},"link":"https://g0v-tw.kktix.cc/events/g0v-hackath4n-taipei"},{"id":"2c74f496-ab40-4b15-b4a1-7f376a63c0b8","projectId":"70e932c0-cb50-40f9-aba0-ced935f2d5de","name":"g0v XD-talking-pre-hackath4n 跨設計哈拉松","type":"實體活動","description":"8/10 的國民大會黑客松之前，先來做點什麼吧！ 主題：Whatever - btw，XDesign 跨設計社群的負責人 Roy 會來被大家推坑 XD 可能的專案：https://g0v.hackpa","startDate":"2013-07-19T10:00:00.000Z","endDate":"2013-07-19T14:00:00.000Z","annouceToContributors":false,"location":{"name":"和多聯合辦公室","address":"台北市大安區忠孝東路四段170巷17弄12號2樓"},"link":"https://g0v-tw.kktix.cc/events/g0v-xd-talking-pre-hackath4n"},{"id":"a46d0522-1335-4d69-ae1b-393552e411cf","projectId":"70e932c0-cb50-40f9-aba0-ced935f2d5de","name":"g0v 緊急黑客松後松","type":"實體活動","description":"因為 walkingice 要到台北蹲一天，反正大家如果在家沒出門也是在用電腦，不如一塊來黑客松吧。   共筆：https://g0v.hackpad.com/g0v-post-hackath3n-S","startDate":"2013-06-23T02:00:00.000Z","endDate":"2013-06-23T10:00:00.000Z","annouceToContributors":false,"location":{"name":"和多聯合辦公室","address":"台北市大安區忠孝東路四段170巷17弄12號2樓"},"link":"https://g0v-tw.kktix.cc/events/g0v-post-hackath3n"},{"id":"4f338a3b-357c-4795-8ad7-c55233d64fd7","projectId":"70e932c0-cb50-40f9-aba0-ced935f2d5de","name":"g0v.tw hackath3n | 台灣零時政府第參次客廳工廠黑客松 - 台北場","type":"實體活動","description":"【號外！】此次黑客松增設最佳專案獎或最佳貢獻獎，獎品備有 COSCUP 門票四張。（感謝 @hlb、@pofeng、＠legist 提供個人贊助票，@ronnywang 提供VIP票券） 【為何要","startDate":"2013-06-08T01:00:00.000Z","endDate":"2013-06-08T10:00:00.000Z","annouceToContributors":false,"location":{"name":"中研院資訊科學研究所","address":"台北市南港區研究院路二段128號"},"link":"https://g0v-tw.kktix.cc/events/g0v-hackath3n-taipei"},{"id":"a3efd502-65cc-4a9b-a039-bb6e53be5f75","projectId":"70e932c0-cb50-40f9-aba0-ced935f2d5de","name":"g0v post-pre-hackath3n","type":"實體活動","description":"6/8 的客廳工廠黑客松之前的 pre-hackath3n 之後但仍是在 6/8 的客廳工廠黑客松之前，先來做點什麼吧！ 主題：讓黑客松效果更佳 希望偏重在協作工具、共用資料等等。不過也歡迎實作特定專","startDate":"2013-06-06T10:30:00.000Z","endDate":"2013-06-06T12:30:00.000Z","annouceToContributors":false,"location":{"name":"和多聯合辦公室","address":"台北市大安區忠孝東路四段170巷17弄12號2樓"},"link":"https://g0v-tw.kktix.cc/events/g0v-postprehackath3n"},{"id":"87f80694-6dc3-49e4-bcf4-2bf921871043","projectId":"70e932c0-cb50-40f9-aba0-ced935f2d5de","name":"g0v.tw hackath2n | 台灣零時政府第貳次九大建設黑客松 - 台北場","type":"實體活動","description":"（如果你是 Android 開發者，也可以考慮選擇參加 GTUG 舉辦的 Android Hackathon, 該活動中也可以進行 g0v 相關的主題！） 【為何要來】g0v.tw 是一個致力於打造資","startDate":"2013-03-23T01:00:00.000Z","endDate":"2013-03-23T10:00:00.000Z","annouceToContributors":false,"location":{"name":"中研院資訊科學研究所","address":"台北市南港區研究院路二段128號"},"link":"https://g0v-tw.kktix.cc/events/g0v-hackath2n-taipei"},{"id":"609272a2-5464-47f0-ab19-3faaba0ccfda","projectId":"70e932c0-cb50-40f9-aba0-ced935f2d5de","name":"g0v.tw hackath1n | 台灣零時政府第壹次公地放領黑客松 - 台北場","type":"實體活動","description":"這裡是台北場的報名頁面，參加台中場的朋友請至 http://registrano.com/events/g0v-hackath1n-taichung 報名。參加高雄場的朋友請至 http://regi","startDate":"2013-01-27T01:00:00.000Z","endDate":"2013-01-27T10:00:00.000Z","annouceToContributors":false,"location":{"name":"中研院資訊科學研究所","address":"台北市南港區研究院路二段128號"},"link":"https://g0v-tw.kktix.cc/events/g0v-hackath1n"},{"id":"50cd724f-98e2-423a-8860-3d8d29d6b4d0","projectId":"70e932c0-cb50-40f9-aba0-ced935f2d5de","name":"g0v.tw hackath1n | 台灣零時政府第壹次公地放領黑客松 - 台中場","type":"實體活動","description":"這裡是台中場的報名頁面，參加台北場的朋友請至 http://registrano.com/events/g0v-hackath1n 報名。參加高雄場的朋友請至 http://registrano.co","startDate":"2013-01-27T01:00:00.000Z","endDate":"2013-01-27T10:00:00.000Z","annouceToContributors":false,"location":{"name":"默契咖啡","address":"台中市407中港路二段60-3號 電話：04-2313-4597  營業時間：9:00 am～11:00 pm"},"link":"https://g0v-tw.kktix.cc/events/g0v-hackath1n-taichung"},{"id":"9d54ae45-b529-487d-8b46-1fc3a011b860","projectId":"70e932c0-cb50-40f9-aba0-ced935f2d5de","name":"g0v.tw hackath1n | 台灣零時政府第壹次公地放領黑客松 - 高雄場","type":"實體活動","description":"這裡是高雄場的報名頁面，參加台北場的朋友請至 http://registrano.com/events/g0v-hackath1n 報名，台中場的朋友請至 http://registrano.com/","startDate":"2013-01-27T01:00:00.000Z","endDate":"2013-01-27T10:00:00.000Z","annouceToContributors":false,"location":{"name":"高雄軟體園區B棟708會議室","address":"高雄市前鎮區復興四路12號 B708 電話：07-9700910分機16"},"link":"https://g0v-tw.kktix.cc/events/g0v-hackath1n-kaohsiung"},{"id":"26f2bce6-7032-41f4-825b-1d52acd6a3d9","projectId":"70e932c0-cb50-40f9-aba0-ced935f2d5de","name":"g0v.tw hackath0n | 台灣零時政府第零次動員戡亂黑客松","type":"實體活動","description":"台灣零時政府第零次動員戡亂黑客松 請注意！場地已變更至「中研院資創中心 」 感謝大家的熱情參與，本活動已額滿！若有興趣參與，請上 hackpad  與 irc 討論有興趣的主題。活動當天的開場介紹及結","startDate":"2012-12-01T01:00:00.000Z","endDate":"2012-12-01T10:00:00.000Z","annouceToContributors":false,"location":{"name":"中研院資訊科技創新研究中心","address":"台北市南港區研究院路二段128號"},"link":"https://g0v-tw.kktix.cc/events/dab224"},{"id":"c6977a05-280f-4faf-9fd8-bd88c7b24a9d","projectId":"70e932c0-cb50-40f9-aba0-ced935f2d5de","name":"g0v hackath10n | 台灣零時政府第拾次資料科學黑客松","type":"實體活動","description":"g0v Summit 第二天「開放工作坊」 ☞  Unconference  時間：2014/11/9 0900-1800 地點：中央研究院 資訊科學研究所 議程：http://summit.g0","startDate":"","endDate":"","annouceToContributors":false,"guestLimit":0,"attendanceCount":0,"location":{"name":"中央研究院人資訊科學研究所  (Institution of Information Science of Academia Sinica)","address":"台北市南港區研究院路二段128號 (No.128, Sec. 2, Academia Rd., Nangang Dist., Taipei City 115, Taiwan)"},"link":"https://beta.hackfoldr.org/g0v-hackath10n"}]